Workbook

Sheet Comparativo
A1: INDUSTRIA SCHUMACHER LTDA
A2: Demonstração do Resultado do Exercício (DRE) – Comparativo mensal
A3: Período: 01/01/2026 a 31/08/2026 (valores mensais) | Filial: CONSOLIDADO
A4: CNPJ: 04.589.817/0001-06
A5: Valores em R$ (reais). Fonte: relatório do sistema contábil (PDF), convertido sem alteração de valores.
A7: Conta | B7: Jan/26 | C7: Fev/26 | D7: Mar/26 | E7: Abr/26 | F7: Mai/26 | G7: Jun/26 | H7: Jul/26 | I7: Ago/26 | J7: Acumulado Jan–Ago
A8: RECEITA OPERACIONAL BRUTA | B8: ='Jan-26'!B8 -> 65256171 | C8: ='Fev-26'!B8 -> 4421800.7 | D8: ='Mar-26'!B8 -> 5895674.1 | E8: ='Abr-26'!B8 -> 4724378.4 | F8: ='Mai-26'!B8 -> 4982409 | G8: ='Jun-26'!B8 -> 5521005 | H8: ='Jul-26'!B8 -> 5702251 | I8: ='Ago-26'!B8 -> 5448307.6 | J8: =SUM(B8:I8) -> 1.01952e+08
A9: RECEITAS DE VENDAS | B9: ='Jan-26'!B9 -> 66077106 | C9: ='Fev-26'!B9 -> 4726850.5 | D9: ='Mar-26'!B9 -> 6009654.5 | E9: ='Abr-26'!B9 -> 4736464.6 | F9: ='Mai-26'!B9 -> 4698899.2 | G9: ='Jun-26'!B9 -> 6249304.5 | H9: ='Jul-26'!B9 -> 5895604.8 | I9: ='Ago-26'!B9 -> 5683386 | J9: =SUM(B9:I9) -> 1.0407727e+08
A10: VENDAS MERCADO INTERNO | B10: ='Jan-26'!B10 -> 66077106 | C10: ='Fev-26'!B10 -> 4726850.5 | D10: ='Mar-26'!B10 -> 6009654.5 | E10: ='Abr-26'!B10 -> 4736464.6 | F10: ='Mai-26'!B10 -> 4698899.2 | G10: ='Jun-26'!B10 -> 6249304.5 | H10: ='Jul-26'!B10 -> 5895604.8 | I10: ='Ago-26'!B10 -> 5683386 | J10: =SUM(B10:I10) -> 1.0407727e+08
A11: VENDA PROD. IND. EM OP. CONTA PROPRIA (RESULTADO) | B11: ='Jan-26'!B11 -> 36324920 | C11: ='Fev-26'!B11 -> 4710051 | D11: ='Mar-26'!B11 -> 5991540.5 | E11: ='Abr-26'!B11 -> 4715511.1 | F11: ='Mai-26'!B11 -> 4682776.2 | G11: ='Jun-26'!B11 -> 6235791.5 | H11: ='Jul-26'!B11 -> 5863520.3 | I11: ='Ago-26'!B11 -> 5667516.5 | J11: =SUM(B11:I11) -> 74191627
A12: FATURAMENTO CFE. DL1598/77 ART.12 ITEM I | B12: ='Jan-26'!B12 -> 29520870 | J12: =SUM(B12:I12) -> 29520870
A13: VENDA DE SUCATA/ RESIDUO/ RECICLADOS | B13: ='Jan-26'!B13 -> 231315.75 | C13: ='Fev-26'!B12 -> 16799.41 | D13: ='Mar-26'!B12 -> 18114 | E13: ='Abr-26'!B12 -> 20953.49 | F13: ='Mai-26'!B12 -> 16123 | G13: ='Jun-26'!B12 -> 13513 | H13: ='Jul-26'!B12 -> 32084.5 | I13: ='Ago-26'!B12 -> 15869.6 | J13: =SUM(B13:I13) -> 364772.75
A14: VENDAS MERCADO EXTERNO | B14: ='Jan-26'!B14 -> 7093786.6 | C14: ='Fev-26'!B13 -> 211332.15 | D14: ='Mar-26'!B13 -> 714871.99 | E14: ='Abr-26'!B13 -> 605033.01 | F14: ='Mai-26'!B13 -> 720828.08 | G14: ='Jun-26'!B13 -> 462652.85 | H14: ='Jul-26'!B13 -> 390744.11 | I14: ='Ago-26'!B13 -> 308252.92 | J14: =SUM(B14:I14) -> 10507502
A15: VENDA DESTINADA A EXPORTACAO | B15: ='Jan-26'!B15 -> 2527913.2 | C15: ='Fev-26'!B14 -> 199345.15 | D15: ='Mar-26'!B14 -> 185945.39 | E15: ='Abr-26'!B14 -> 237498.65 | F15: ='Mai-26'!B14 -> 104523.32 | G15: ='Jun-26'!B14 -> 322203.11 | H15: ='Jul-26'!B14 -> 42378.34 | I15: ='Ago-26'!B14 -> 268734.72 | J15: =SUM(B15:I15) -> 3888541.9
A16: EXPORTACAO PROPRIA | B16: ='Jan-26'!B16 -> 4475893.3 | C16: ='Fev-26'!B15 -> 11987 | D16: ='Mar-26'!B15 -> 528926.6 | E16: ='Abr-26'!B15 -> 367534.36 | F16: ='Mai-26'!B15 -> 616304.76 | G16: ='Jun-26'!B15 -> 140449.74 | H16: ='Jul-26'!B15 -> 348365.77 | I16: ='Ago-26'!B15 -> 39518.2 | J16: =SUM(B16:I16) -> 6528979.8
A17: VENDA PRA DRAWBACK | B17: ='Jan-26'!B17 -> 5265 | J17: =SUM(B17:I17) -> 5265
A18: VENDA PROD. CONSIGNADO DEST. A EXPORTACAO | B18: ='Jan-26'!B18 -> 84715.1 | J18: =SUM(B18:I18) -> 84715.1
A19: SERVIÇOS MERCADO INTERNO | B19: ='Jan-26'!B19 -> 3083029.6 | C19: ='Fev-26'!B16 -> 189429.19 | D19: ='Mar-26'!B16 -> 292393.44 | E19: ='Abr-26'!B16 -> 324413.42 | F19: ='Mai-26'!B16 -> 323104.2 | G19: ='Jun-26'!B16 -> 425153.82 | H19: ='Jul-26'!B16 -> 350984.55 | I19: ='Ago-26'!B16 -> 370038.22 | J19: =SUM(B19:I19) -> 5358546.4
A20: INDUSTRIALIZACAO EFETUADA A TERCEIROS | B20: ='Jan-26'!B20 -> 2617837.2 | C20: ='Fev-26'!B17 -> 152965.49 | D20: ='Mar-26'!B17 -> 168743.86 | E20: ='Abr-26'!B17 -> 214665.07 | F20: ='Mai-26'!B17 -> 194366.82 | G20: ='Jun-26'!B17 -> 270329.01 | H20: ='Jul-26'!B17 -> 203764.46 | I20: ='Ago-26'!B17 -> 234613.03 | J20: =SUM(B20:I20) -> 4057284.9
A21: PRESTACAO DE SERVICOS | B21: ='Jan-26'!B21 -> 465192.39 | C21: ='Fev-26'!B18 -> 36463.7 | D21: ='Mar-26'!B18 -> 123649.58 | E21: ='Abr-26'!B18 -> 109748.35 | F21: ='Mai-26'!B18 -> 128737.38 | G21: ='Jun-26'!B18 -> 154824.81 | H21: ='Jul-26'!B18 -> 147220.09 | I21: ='Ago-26'!B18 -> 135425.19 | J21: =SUM(B21:I21) -> 1301261.5
A22: (-) IMPOSTOS SOBRE VENDAS | B22: ='Jan-26'!B22 -> 10997751 | C22: ='Fev-26'!B19 -> 705811.06 | D22: ='Mar-26'!B19 -> 1121245.9 | E22: ='Abr-26'!B19 -> 941532.59 | F22: ='Mai-26'!B19 -> 760422.52 | G22: ='Jun-26'!B19 -> 1616106.2 | H22: ='Jul-26'!B19 -> 935082.47 | I22: ='Ago-26'!B19 -> 913369.58 | J22: =SUM(B22:I22) -> 17991321
A23: IPI S/ VENDAS | B23: ='Jan-26'!B23 -> 486086.4 | C23: ='Fev-26'!B20 -> 35801.85 | D23: ='Mar-26'!B20 -> 39340.04 | E23: ='Abr-26'!B20 -> 27921.59 | F23: ='Mai-26'!B20 -> 34455.93 | G23: ='Jun-26'!B20 -> 41102.4 | H23: ='Jul-26'!B20 -> 39049.03 | I23: ='Ago-26'!B20 -> 41557.42 | J23: =SUM(B23:I23) -> 745314.66
A24: ICMS S/ VENDAS | B24: ='Jan-26'!B24 -> 7816591.2 | C24: ='Fev-26'!B21 -> 562883.31 | D24: ='Mar-26'!B21 -> 709755.95 | E24: ='Abr-26'!B21 -> 742405.23 | F24: ='Mai-26'!B21 -> 545460.16 | G24: ='Jun-26'!B21 -> 807399.58 | H24: ='Jul-26'!B21 -> 691676.03 | I24: ='Ago-26'!B21 -> 669571.08 | J24: =SUM(B24:I24) -> 12545743
A25: PIS S/ VENDAS | B25: ='Jan-26'!B25 -> 244816.06 | C25: ='Fev-26'!B22 -> 15080.93 | D25: ='Mar-26'!B22 -> 18368.97 | E25: ='Abr-26'!B22 -> 26434 | F25: ='Mai-26'!B22 -> 26300.24 | G25: ='Jun-26'!B22 -> 33146.27 | H25: ='Jul-26'!B22 -> 30270.24 | I25: ='Ago-26'!B22 -> 30453.6 | J25: =SUM(B25:I25) -> 424870.31
A26: COFINS S/ VENDAS | B26: ='Jan-26'!B26 -> 1124298.7 | C26: ='Fev-26'!B23 -> 69604.27 | D26: ='Mar-26'!B23 -> 84795.93 | E26: ='Abr-26'!B23 -> 122002.84 | F26: ='Mai-26'!B23 -> 121387.11 | G26: ='Jun-26'!B23 -> 152982.81 | H26: ='Jul-26'!B23 -> 139437.49 | I26: ='Ago-26'!B23 -> 140251.49 | J26: =SUM(B26:I26) -> 1954760.7
A27: ISSQN S/ SERVICOS | B27: ='Jan-26'!B27 -> 13955.84 | C27: ='Fev-26'!B24 -> 1093.89 | D27: ='Mar-26'!B24 -> 3709.48 | E27: ='Abr-26'!B24 -> 3292.44 | F27: ='Mai-26'!B24 -> 3862.14 | G27: ='Jun-26'!B24 -> 4644.74 | H27: ='Jul-26'!B24 -> 4416.6 | I27: ='Ago-26'!B24 -> 4062.76 | J27: =SUM(B27:I27) -> 39037.89
A28: ICMS-ST S/ VENDAS | B28: ='Jan-26'!B28 -> 252215.84 | C28: ='Fev-26'!B25 -> 21186.4 | D28: ='Mar-26'!B25 -> 23751.57 | E28: ='Abr-26'!B25 -> 19437.86 | F28: ='Mai-26'!B25 -> 28674.19 | G28: ='Jun-26'!B25 -> 25831.69 | H28: ='Jul-26'!B25 -> 29946.95 | I28: ='Ago-26'!B25 -> 27473.23 | J28: =SUM(B28:I28) -> 428517.73
A29: ICMS DIFAL SOBRE AS VENDAS | B29: ='Jan-26'!B29 -> 1082.44 | C29: ='Fev-26'!B26 -> 160.41 | D29: ='Mar-26'!B26 -> 142.28 | E29: ='Abr-26'!B26 -> 38.63 | F29: ='Mai-26'!B26 -> 282.75 | G29: ='Jun-26'!B26 -> 453.21 | H29: ='Jul-26'!B26 -> 286.13 | J29: =SUM(B29:I29) -> 2445.85
A30: IRPJ RETIDO S/ VENDAS | B30: ='Jan-26'!B30 -> 680737.75 | D30: ='Mar-26'!B27 -> 159103.54 | G30: ='Jun-26'!B27 -> 327175.48 | J30: =SUM(B30:I30) -> 1167016.8
A31: CSLL RETIDO S/ VENDAS | B31: ='Jan-26'!B31 -> 377966.39 | D31: ='Mar-26'!B28 -> 82278.1 | G31: ='Jun-26'!B28 -> 223369.99 | J31: =SUM(B31:I31) -> 683614.48
A32: DEDUÇÕES DA RECEITA BRUTA | B32: ='Jan-26'!B32 -> -445730.17 | C32: ='Fev-26'!B27 -> -45725.46 | D32: ='Mar-26'!B29 -> -2385.15 | E32: ='Abr-26'!B27 -> -9701.07 | F32: ='Mai-26'!B27 -> -2190.96 | G32: ='Jun-26'!B29 -> -864.34 | H32: ='Jul-26'!B27 -> -4009.96 | I32: ='Ago-26'!B26 -> -1527.21 | J32: =SUM(B32:I32) -> -512134.32
A33: (-) DEDUCOES DAS VENDAS | B33: ='Jan-26'!B33 -> 445730.17 | C33: ='Fev-26'!B28 -> 45725.46 | D33: ='Mar-26'!B30 -> 2385.15 | E33: ='Abr-26'!B28 -> 9701.07 | F33: ='Mai-26'!B28 -> 2190.96 | G33: ='Jun-26'!B30 -> 864.34 | H33: ='Jul-26'!B28 -> 4009.96 | I33: ='Ago-26'!B27 -> 1527.21 | J33: =SUM(B33:I33) -> 512134.32
A34: (-) CANCELAMENTOS E DEVOLUCOES | B34: ='Jan-26'!B34 -> 445730.17 | C34: ='Fev-26'!B29 -> 45725.46 | D34: ='Mar-26'!B31 -> 2385.15 | E34: ='Abr-26'!B29 -> 9701.07 | F34: ='Mai-26'!B29 -> 2190.96 | G34: ='Jun-26'!B31 -> 864.34 | H34: ='Jul-26'!B29 -> 4009.96 | I34: ='Ago-26'!B28 -> 1527.21 | J34: =SUM(B34:I34) -> 512134.32
A35: VENDAS CANCELADAS/ESTORNADAS | B35: ='Jan-26'!B35 -> 303435.11 | C35: ='Fev-26'!B30 -> 42575.8 | E35: ='Abr-26'!B30 -> 4389.57 | F35: ='Mai-26'!B30 -> 1315.14 | H35: ='Jul-26'!B30 -> 1338.6 | J35: =SUM(B35:I35) -> 353054.22
A36: EXPORTACAO CANCELADA/ DEVOLVIDA | B36: ='Jan-26'!B36 -> 6939 | J36: =SUM(B36:I36) -> 6939
A37: DEVOLUCAO DE VENDAS | B37: ='Jan-26'!B37 -> 101572.91 | C37: ='Fev-26'!B31 -> 3149.66 | D37: ='Mar-26'!B32 -> 2385.15 | E37: ='Abr-26'!B31 -> 5311.5 | F37: ='Mai-26'!B31 -> 875.82 | G37: ='Jun-26'!B32 -> 864.34 | H37: ='Jul-26'!B31 -> 2671.36 | I37: ='Ago-26'!B29 -> 1527.21 | J37: =SUM(B37:I37) -> 118357.95
A38: (-) CANCELAMENTO DE INDUSTRIALIZACAO | B38: ='Jan-26'!B38 -> 33783.15 | J38: =SUM(B38:I38) -> 33783.15
A39: RECEITA LÍQUIDA | B39: ='Jan-26'!B39 -> 64810441 | C39: ='Fev-26'!B32 -> 4376075.3 | D39: ='Mar-26'!B33 -> 5893289 | E39: ='Abr-26'!B32 -> 4714677.3 | F39: ='Mai-26'!B32 -> 4980218 | G39: ='Jun-26'!B33 -> 5520140.7 | H39: ='Jul-26'!B32 -> 5698241.1 | I39: ='Ago-26'!B30 -> 5446780.4 | J39: =SUM(B39:I39) -> 1.0143986e+08
A40: CUSTOS | B40: ='Jan-26'!B40 -> -43222401 | C40: ='Fev-26'!B33 -> -4756213.8 | D40: ='Mar-26'!B34 -> -7546765.7 | E40: ='Abr-26'!B33 -> -4933376 | F40: ='Mai-26'!B33 -> -5181524.7 | G40: ='Jun-26'!B34 -> -5538137.2 | H40: ='Jul-26'!B33 -> -4788917.3 | I40: ='Ago-26'!B31 -> -4398210.6 | J40: =SUM(B40:I40) -> -80365546
A41: CUSTOS DOS PRODUTOS VENDIDOS | B41: ='Jan-26'!B41 -> 43222401 | C41: ='Fev-26'!B34 -> 4756213.8 | D41: ='Mar-26'!B35 -> 7546765.7 | E41: ='Abr-26'!B34 -> 4933376 | F41: ='Mai-26'!B34 -> 5181524.7 | G41: ='Jun-26'!B35 -> 5538137.2 | H41: ='Jul-26'!B34 -> 4788917.3 | I41: ='Ago-26'!B32 -> 4398210.6 | J41: =SUM(B41:I41) -> 80365546
A42: CUSTO DOS PRODUTOS VENDIDOS | B42: ='Jan-26'!B42 -> 30146592 | C42: ='Fev-26'!B35 -> 3427773.3 | D42: ='Mar-26'!B36 -> 5946277.6 | E42: ='Abr-26'!B35 -> 3349307.1 | F42: ='Mai-26'!B35 -> 3594072.8 | G42: ='Jun-26'!B36 -> 3912429 | H42: ='Jul-26'!B35 -> 3287214 | I42: ='Ago-26'!B33 -> 2697211 | J42: =SUM(B42:I42) -> 56360877
A43: CPV - CUSTO DOS PRODUTOS VENDIDOS | B43: ='Jan-26'!B43 -> 5219.26 | J43: =SUM(B43:I43) -> 5219.26
A44: CPV - CUSTO PRODUTOS VENDIDOS | B44: ='Jan-26'!B44 -> 28929083 | C44: ='Fev-26'!B36 -> 3369397.8 | D44: ='Mar-26'!B37 -> 5833100.7 | E44: ='Abr-26'!B36 -> 3255247 | F44: ='Mai-26'!B36 -> 3493708.9 | G44: ='Jun-26'!B37 -> 3844973.3 | H44: ='Jul-26'!B36 -> 3180895 | I44: ='Ago-26'!B34 -> 2590795.6 | J44: =SUM(B44:I44) -> 54497202
A45: CSP - CUSTO SERVICOS PRESTADOS | B45: ='Jan-26'!B45 -> 40452.82 | F45: ='Mai-26'!B37 -> 7048.83 | G45: ='Jun-26'!B38 -> 2758.87 | H45: ='Jul-26'!B37 -> 2545.62 | J45: =SUM(B45:I45) -> 52806.14
A46: SERVICOS DE INDUSTRIALIZACAO | B46: ='Jan-26'!B46 -> 1182275.4 | C46: ='Fev-26'!B37 -> 58375.5 | D46: ='Mar-26'!B38 -> 113176.89 | E46: ='Abr-26'!B37 -> 94060.04 | F46: ='Mai-26'!B38 -> 93315.11 | G46: ='Jun-26'!B39 -> 64696.78 | H46: ='Jul-26'!B38 -> 103773.34 | I46: ='Ago-26'!B35 -> 106415.38 | J46: =SUM(B46:I46) -> 1816088.5
A47: OUTROS CUSTOS DIRETOS DE FABRICACAO | B47: ='Jan-26'!B47 -> 2204984.4 | C47: ='Fev-26'!B38 -> 331944.53 | D47: ='Mar-26'!B39 -> 372255.56 | E47: ='Abr-26'!B38 -> 501384.07 | F47: ='Mai-26'!B39 -> 512261.92 | G47: ='Jun-26'!B40 -> 573521.93 | H47: ='Jul-26'!B39 -> 498994.24 | I47: ='Ago-26'!B36 -> 579028.82 | J47: =SUM(B47:I47) -> 5574375.5
A48: OUTROS CUSTOS DIRETOS DE FABRICACAO | B48: ='Jan-26'!B48 -> 2204984.4 | C48: ='Fev-26'!B39 -> 331944.53 | D48: ='Mar-26'!B40 -> 372255.56 | E48: ='Abr-26'!B39 -> 501384.07 | F48: ='Mai-26'!B40 -> 512261.92 | G48: ='Jun-26'!B41 -> 573521.93 | H48: ='Jul-26'!B40 -> 498994.24 | I48: ='Ago-26'!B37 -> 579028.82 | J48: =SUM(B48:I48) -> 5574375.5
A49: GAS - USO INDUSTRIAL | B49: ='Jan-26'!B49 -> 1119229.6 | C49: ='Fev-26'!B40 -> 98203.54 | D49: ='Mar-26'!B41 -> 87965.18 | E49: ='Abr-26'!B40 -> 75710.68 | F49: ='Mai-26'!B41 -> 77769.13 | G49: ='Jun-26'!B42 -> 124340.65 | H49: ='Jul-26'!B41 -> 62568.16 | I49: ='Ago-26'!B38 -> 98148.01 | J49: =SUM(B49:I49) -> 1743934.9
A50: FRETES SOBRE VENDAS | B50: ='Jan-26'!B50 -> 517643.94 | C50: ='Fev-26'!B41 -> 30019.13 | D50: ='Mar-26'!B42 -> 44957.03 | E50: ='Abr-26'!B41 -> 38900.44 | F50: ='Mai-26'!B42 -> 30456.15 | G50: ='Jun-26'!B43 -> 39688.93 | H50: ='Jul-26'!B42 -> 40767.68 | I50: ='Ago-26'!B39 -> 44237.43 | J50: =SUM(B50:I50) -> 786670.73
A51: COMBUSTIVEIS E LUBRIFICANTES (TRANSP. MERC.) | B51: ='Jan-26'!B51 -> 277642.76 | C51: ='Fev-26'!B42 -> 25899.16 | D51: ='Mar-26'!B43 -> 37457.61 | E51: ='Abr-26'!B42 -> 37374.88 | F51: ='Mai-26'!B43 -> 23476.58 | G51: ='Jun-26'!B44 -> 30338.15 | H51: ='Jul-26'!B43 -> 32054.19 | I51: ='Ago-26'!B40 -> 29725.93 | J51: =SUM(B51:I51) -> 493969.26
A52: DEPRECIACAO IMOBILIZADO PRODUCAO | B52: ='Jan-26'!B52 -> 290468.18 | C52: ='Fev-26'!B43 -> 177822.7 | D52: ='Mar-26'!B44 -> 201875.74 | E52: ='Abr-26'!B43 -> 349398.07 | F52: ='Mai-26'!B44 -> 380560.06 | G52: ='Jun-26'!B45 -> 379154.2 | H52: ='Jul-26'!B44 -> 363604.21 | I52: ='Ago-26'!B41 -> 406917.45 | J52: =SUM(B52:I52) -> 2549800.6
A53: FOLHA, BENEFICIOS E ENCARGOS - PRODUÇÃO | B53: ='Jan-26'!B53 -> 10870824 | C53: ='Fev-26'!B44 -> 996495.99 | D53: ='Mar-26'!B45 -> 1228232.6 | E53: ='Abr-26'!B44 -> 1082684.9 | F53: ='Mai-26'!B45 -> 1075189.9 | G53: ='Jun-26'!B46 -> 1052186.4 | H53: ='Jul-26'!B45 -> 1002709.1 | I53: ='Ago-26'!B42 -> 1121970.9 | J53: =SUM(B53:I53) -> 18430294
A54: SALARIOS E ORDENADOS - PRODUCAO | B54: ='Jan-26'!B54 -> 6796883 | C54: ='Fev-26'!B45 -> 609113.42 | D54: ='Mar-26'!B46 -> 640251.74 | E54: ='Abr-26'!B45 -> 625118.23 | F54: ='Mai-26'!B46 -> 650673.48 | G54: ='Jun-26'!B47 -> 628132.38 | H54: ='Jul-26'!B46 -> 593399.59 | I54: ='Ago-26'!B43 -> 690898.85 | J54: =SUM(B54:I54) -> 11234471
A55: RESCISOES/INDENIZACOES - PRODUCAO | B55: ='Jan-26'!B55 -> 73548 | C55: ='Fev-26'!B46 -> 13624 | D55: ='Mar-26'!B47 -> 3764.13 | E55: ='Abr-26'!B46 -> 8782.77 | F55: ='Mai-26'!B47 -> 2217.81 | G55: ='Jun-26'!B48 -> 7970.78 | H55: ='Jul-26'!B47 -> 9426.13 | I55: ='Ago-26'!B44 -> 1476.02 | J55: =SUM(B55:I55) -> 120809.64
A56: TREINAMENTOS/CURSOS - PRODUCAO | B56: ='Jan-26'!B56 -> 1524.58 | J56: =SUM(B56:I56) -> 1524.58
A57: DESPESAS COM ACIDENTE DE TRABALHO | B57: ='Jan-26'!B57 -> 501.12 | J57: =SUM(B57:I57) -> 501.12
A58: SEGURO DE VIDA - PRODUCAO | B58: ='Jan-26'!B58 -> 23557.31 | C58: ='Fev-26'!B47 -> 4149.89 | E58: ='Abr-26'!B47 -> 3516.04 | J58: =SUM(B58:I58) -> 31223.24
A59: FERIAS - PRODUCAO | B59: ='Jan-26'!B59 -> 745851.7 | C59: ='Fev-26'!B48 -> 56258.05 | D59: ='Mar-26'!B48 -> 137066.72 | E59: ='Abr-26'!B48 -> 71521.6 | F59: ='Mai-26'!B48 -> 69778.97 | G59: ='Jun-26'!B49 -> 69629.37 | H59: ='Jul-26'!B48 -> 69367.07 | I59: ='Ago-26'!B45 -> 71261.98 | J59: =SUM(B59:I59) -> 1290735.5
A60: DECIMO TRCEIRO SALARIO - PRODUCAO | B60: ='Jan-26'!B60 -> 641072.21 | C60: ='Fev-26'!B49 -> 41733.09 | D60: ='Mar-26'!B49 -> 102122.9 | E60: ='Abr-26'!B49 -> 53386.82 | F60: ='Mai-26'!B49 -> 52037.43 | G60: ='Jun-26'!B50 -> 52234.6 | H60: ='Jul-26'!B49 -> 52057.77 | I60: ='Ago-26'!B46 -> 52768.65 | J60: =SUM(B60:I60) -> 1047413.5
A61: FGTS - PRODUCAO | B61: ='Jan-26'!B61 -> 577092.55 | C61: ='Fev-26'!B50 -> 52457.44 | D61: ='Mar-26'!B50 -> 50355.81 | E61: ='Abr-26'!B50 -> 52000.6 | F61: ='Mai-26'!B50 -> 52057.86 | G61: ='Jun-26'!B51 -> 49411.85 | H61: ='Jul-26'!B50 -> 49823.22 | I61: ='Ago-26'!B47 -> 55129.89 | J61: =SUM(B61:I61) -> 938329.22
A62: INSS - PRODUCAO | B62: ='Jan-26'!B62 -> 1338508.6 | C62: ='Fev-26'!B51 -> 197568.71 | D62: ='Mar-26'!B51 -> 186318.8 | E62: ='Abr-26'!B51 -> 190801.82 | F62: ='Mai-26'!B51 -> 191885.32 | G62: ='Jun-26'!B52 -> 184381.6 | H62: ='Jul-26'!B51 -> 184252.44 | I62: ='Ago-26'!B48 -> 204205.94 | J62: =SUM(B62:I62) -> 2677923.2
A63: CPRB - PRODUCAO | B63: ='Jan-26'!B63 -> 471146.04 | J63: =SUM(B63:I63) -> 471146.04
A64: FGTS S/ FERIAS - PRODUCAO | B64: ='Jan-26'!B64 -> 92431.77 | C64: ='Fev-26'!B52 -> 6113.54 | D64: ='Mar-26'!B52 -> 11136.46 | E64: ='Abr-26'!B52 -> 5720.75 | F64: ='Mai-26'!B52 -> 5581.41 | G64: ='Jun-26'!B53 -> 5569.44 | H64: ='Jul-26'!B52 -> 4666.92 | I64: ='Ago-26'!B49 -> 5700 | J64: =SUM(B64:I64) -> 136920.29
A65: INSS S/ FERIAS | D65: ='Mar-26'!B53 -> 40959.43 | E65: ='Abr-26'!B53 -> 20938.25 | F65: ='Mai-26'!B53 -> 20434.29 | G65: ='Jun-26'!B54 -> 20386.38 | H65: ='Jul-26'!B53 -> 20310.86 | I65: ='Ago-26'!B50 -> 20862.99 | J65: =SUM(B65:I65) -> 143892.2
A66: INSS S/ DECIMO TERCEIRO - PRODUCAO | B66: ='Jan-26'!B65 -> 59364.12 | C66: ='Fev-26'!B53 -> 12139.36 | D66: ='Mar-26'!B54 -> 30087.67 | E66: ='Abr-26'!B54 -> 15628.07 | F66: ='Mai-26'!B54 -> 15237.35 | G66: ='Jun-26'!B55 -> 15292.04 | H66: ='Jul-26'!B54 -> 15241.26 | I66: ='Ago-26'!B51 -> 15445.92 | J66: =SUM(B66:I66) -> 178435.79
A67: FGTS S/ DECIMO TERCEIRO - PRODUCAO | B67: ='Jan-26'!B66 -> 49343.19 | C67: ='Fev-26'!B54 -> 3338.49 | D67: ='Mar-26'!B55 -> 8168.92 | E67: ='Abr-26'!B55 -> 4269.96 | F67: ='Mai-26'!B55 -> 4162.08 | G67: ='Jun-26'!B56 -> 4177.93 | H67: ='Jul-26'!B55 -> 4163.81 | I67: ='Ago-26'!B52 -> 4220.61 | J67: =SUM(B67:I67) -> 81844.99
A68: DESPESAS JUDICIAIS - FOLHA PAGTO | D68: ='Mar-26'!B56 -> 18000 | E68: ='Abr-26'!B56 -> 31000 | F68: ='Mai-26'!B56 -> 15559.54 | G68: ='Jun-26'!B57 -> 15000 | J68: =SUM(B68:I68) -> 79559.54
A69: LUCRO BRUTO | B69: ='Jan-26'!B67 -> 21588040 | C69: ='Fev-26'!B55 -> -380138.51 | D69: ='Mar-26'!B57 -> -1653476.8 | E69: ='Abr-26'!B57 -> -218698.69 | F69: ='Mai-26'!B57 -> -201306.66 | G69: ='Jun-26'!B58 -> -17996.59 | H69: ='Jul-26'!B56 -> 909323.81 | I69: ='Ago-26'!B53 -> 1048569.8 | J69: =SUM(B69:I69) -> 21074316
A70: DESPESAS OPERACIONAIS | B70: ='Jan-26'!B68 -> -16969981 | C70: ='Fev-26'!B56 -> -1179795.2 | D70: ='Mar-26'!B58 -> -1352282.2 | E70: ='Abr-26'!B58 -> -1142219.2 | F70: ='Mai-26'!B58 -> -1082135.4 | G70: ='Jun-26'!B59 -> -1101105.2 | H70: ='Jul-26'!B57 -> -1185503.1 | I70: ='Ago-26'!B54 -> -1144173.4 | J70: =SUM(B70:I70) -> -25157195
A71: FOLHA, BENEFICIOS E ENCARGOS | B71: ='Jan-26'!B69 -> 5101903 | C71: ='Fev-26'!B57 -> 316792.55 | D71: ='Mar-26'!B59 -> 367874.74 | E71: ='Abr-26'!B59 -> 328077.09 | F71: ='Mai-26'!B59 -> 522096.79 | G71: ='Jun-26'!B60 -> 424739.14 | H71: ='Jul-26'!B58 -> 352501.71 | I71: ='Ago-26'!B55 -> 424693.59 | J71: =SUM(B71:I71) -> 7838678.6
A72: GASTO COM COLABORADORES | B72: ='Jan-26'!B70 -> 5101903 | C72: ='Fev-26'!B58 -> 316792.55 | D72: ='Mar-26'!B60 -> 367874.74 | E72: ='Abr-26'!B60 -> 328077.09 | F72: ='Mai-26'!B60 -> 522096.79 | G72: ='Jun-26'!B61 -> 424739.14 | H72: ='Jul-26'!B59 -> 352501.71 | I72: ='Ago-26'!B56 -> 424693.59 | J72: =SUM(B72:I72) -> 7838678.6
A73: SALARIOS E ORDENADOS - ADM | B73: ='Jan-26'!B71 -> 1296704.2 | C73: ='Fev-26'!B59 -> 53824.48 | D73: ='Mar-26'!B61 -> 77832.42 | E73: ='Abr-26'!B61 -> 1402.33 | F73: ='Mai-26'!B61 -> 89936.98 | G73: ='Jun-26'!B62 -> 106845.44 | H73: ='Jul-26'!B60 -> 81123.89 | I73: ='Ago-26'!B57 -> 108844.35 | J73: =SUM(B73:I73) -> 1816514.1
A74: GRATIFICACOES E BONUS - ADM | B74: ='Jan-26'!B72 -> 1795690.9 | C74: ='Fev-26'!B60 -> 109331.11 | D74: ='Mar-26'!B62 -> 127758 | E74: ='Abr-26'!B62 -> 143302 | F74: ='Mai-26'!B62 -> 135239.22 | G74: ='Jun-26'!B63 -> 130436.51 | H74: ='Jul-26'!B61 -> 141574.34 | I74: ='Ago-26'!B58 -> 140823 | J74: =SUM(B74:I74) -> 2724155
A75: ESTAGIARIOS/ BOLSISTAS - ADM | I75: ='Ago-26'!B59 -> 40 | J75: =SUM(B75:I75) -> 40
A76: RESCISOES/ INDENIZACOES - ADM | B76: ='Jan-26'!B73 -> 71216.51 | C76: ='Fev-26'!B61 -> 3324 | E76: ='Abr-26'!B63 -> 8639.41 | J76: =SUM(B76:I76) -> 83179.92
A77: ALIMENTACAO NA INDUSTRIA - ADM | B77: ='Jan-26'!B74 -> 116539.93 | C77: ='Fev-26'!B62 -> 15073.89 | D77: ='Mar-26'!B63 -> 5606.02 | E77: ='Abr-26'!B64 -> 7311.69 | F77: ='Mai-26'!B63 -> 16856.04 | G77: ='Jun-26'!B64 -> 10679.96 | H77: ='Jul-26'!B62 -> 11362.71 | I77: ='Ago-26'!B60 -> 13067.36 | J77: =SUM(B77:I77) -> 196497.6
A78: DESPESAS COM EPI - ADM | B78: ='Jan-26'!B75 -> 160213.96 | C78: ='Fev-26'!B63 -> 12311.4 | D78: ='Mar-26'!B64 -> 9026.96 | E78: ='Abr-26'!B65 -> 16248.49 | F78: ='Mai-26'!B64 -> 74657.69 | G78: ='Jun-26'!B65 -> 13056.24 | H78: ='Jul-26'!B63 -> 10081.05 | I78: ='Ago-26'!B61 -> 15319.59 | J78: =SUM(B78:I78) -> 310915.38
A79: EXAMES OCUPACIONAIS - ADM | B79: ='Jan-26'!B76 -> 62475.58 | C79: ='Fev-26'!B64 -> 893.35 | D79: ='Mar-26'!B65 -> 17172.88 | E79: ='Abr-26'!B66 -> 515.53 | F79: ='Mai-26'!B65 -> 1507.14 | G79: ='Jun-26'!B66 -> 31162.25 | H79: ='Jul-26'!B64 -> 683.06 | I79: ='Ago-26'!B62 -> 1572.06 | J79: =SUM(B79:I79) -> 115981.85
A80: TREINAMENTOS/ CURSOS/ SEMINARIOS - ADM | B80: ='Jan-26'!B77 -> 179773.49 | C80: ='Fev-26'!B65 -> 9626.1 | D80: ='Mar-26'!B66 -> 9943.6 | E80: ='Abr-26'!B67 -> 34326.1 | F80: ='Mai-26'!B66 -> 10572.35 | G80: ='Jun-26'!B67 -> 10511.1 | H80: ='Jul-26'!B65 -> 12119.4 | I80: ='Ago-26'!B63 -> 14590.97 | J80: =SUM(B80:I80) -> 281463.11
A81: SEGURO DE VIDA - ADM | B81: ='Jan-26'!B78 -> 12449.68 | D81: ='Mar-26'!B67 -> 4149.89 | E81: ='Abr-26'!B68 -> 633.85 | F81: ='Mai-26'!B67 -> 4297 | G81: ='Jun-26'!B68 -> 4297.01 | H81: ='Jul-26'!B66 -> 4297.01 | I81: ='Ago-26'!B64 -> 4494.9 | J81: =SUM(B81:I81) -> 34619.34
A82: SINDICATO - FABRICA - ADM | B82: ='Jan-26'!B79 -> 13104 | C82: ='Fev-26'!B66 -> 1008 | D82: ='Mar-26'!B68 -> 1088 | E82: ='Abr-26'!B69 -> 1028 | F82: ='Mai-26'!B68 -> 1008 | G82: ='Jun-26'!B69 -> 1008 | H82: ='Jul-26'!B67 -> 1008 | I82: ='Ago-26'!B65 -> 1008 | J82: =SUM(B82:I82) -> 20260
A83: FERIAS - ADM | B83: ='Jan-26'!B80 -> 197679.34 | C83: ='Fev-26'!B67 -> 14428.83 | D83: ='Mar-26'!B69 -> 13401.84 | E83: ='Abr-26'!B70 -> 13373.4 | F83: ='Mai-26'!B69 -> 13309.34 | G83: ='Jun-26'!B70 -> 13307.89 | H83: ='Jul-26'!B68 -> 14117.23 | I83: ='Ago-26'!B66 -> 14497.02 | J83: =SUM(B83:I83) -> 294114.89
A84: DECIMO TERCEIRO SALARIO - ADM | B84: ='Jan-26'!B81 -> 158211.95 | C84: ='Fev-26'!B68 -> 10787.95 | D84: ='Mar-26'!B70 -> 10271.77 | E84: ='Abr-26'!B71 -> 10053.13 | F84: ='Mai-26'!B70 -> 10006.94 | G84: ='Jun-26'!B71 -> 10027.84 | H84: ='Jul-26'!B69 -> 10628.04 | I84: ='Ago-26'!B67 -> 10913.94 | J84: =SUM(B84:I84) -> 230901.56
A85: VALE REFEICAO - ADM | B85: ='Jan-26'!B82 -> 781842 | C85: ='Fev-26'!B69 -> 75077 | D85: ='Mar-26'!B71 -> 78921 | E85: ='Abr-26'!B72 -> 78928 | F85: ='Mai-26'!B71 -> 154111 | G85: ='Jun-26'!B72 -> 82929 | H85: ='Jul-26'!B70 -> 660 | I85: ='Ago-26'!B68 -> 83896 | J85: =SUM(B85:I85) -> 1336364
A86: CONSULTAS/ EXAMES/ MEDICAMENTOS - ADM | B86: ='Jan-26'!B83 -> 18809.54 | C86: ='Fev-26'!B70 -> 748.44 | D86: ='Mar-26'!B72 -> 941.57 | E86: ='Abr-26'!B73 -> 398.16 | F86: ='Mai-26'!B72 -> 237.09 | J86: =SUM(B86:I86) -> 21134.8
A87: DESPESAS C/ CONFRATERNIZACAO - ADM | B87: ='Jan-26'!B84 -> 102537.92 | D87: ='Mar-26'!B73 -> 1402.79 | E87: ='Abr-26'!B74 -> 1559 | G87: ='Jun-26'!B73 -> 119.9 | H87: ='Jul-26'!B71 -> 54488.98 | I87: ='Ago-26'!B69 -> 5268.4 | J87: =SUM(B87:I87) -> 165376.99
A88: PRO-LABORE - ADM | B88: ='Jan-26'!B85 -> 134654 | C88: ='Fev-26'!B71 -> 10358 | D88: ='Mar-26'!B74 -> 10358 | E88: ='Abr-26'!B75 -> 10358 | F88: ='Mai-26'!B73 -> 10358 | G88: ='Jun-26'!B74 -> 10358 | H88: ='Jul-26'!B72 -> 10358 | I88: ='Ago-26'!B70 -> 10358 | J88: =SUM(B88:I88) -> 207160
A89: ENCARGOS FOLHA | B89: ='Jan-26'!B86 -> 808261.2 | C89: ='Fev-26'!B72 -> 82134.35 | D89: ='Mar-26'!B75 -> 76376.26 | E89: ='Abr-26'!B76 -> 79224.68 | F89: ='Mai-26'!B74 -> 56407.89 | G89: ='Jun-26'!B75 -> 75095.58 | H89: ='Jul-26'!B73 -> 59195.61 | I89: ='Ago-26'!B71 -> 71321.45 | J89: =SUM(B89:I89) -> 1308017
A90: FGTS - ADM | B90: ='Jan-26'!B87 -> 129610.73 | C90: ='Fev-26'!B73 -> 9975.6 | D90: ='Mar-26'!B76 -> 9992.57 | E90: ='Abr-26'!B77 -> 9228.62 | F90: ='Mai-26'!B75 -> 9508.61 | G90: ='Jun-26'!B76 -> 9291.47 | H90: ='Jul-26'!B74 -> 9399.41 | I90: ='Ago-26'!B72 -> 10152.27 | J90: =SUM(B90:I90) -> 197159.28
A91: INSS - ADM | B91: ='Jan-26'!B88 -> 316798.59 | C91: ='Fev-26'!B74 -> 41596.32 | D91: ='Mar-26'!B77 -> 39407.43 | E91: ='Abr-26'!B78 -> 38149.57 | F91: ='Mai-26'!B76 -> 38247.88 | G91: ='Jun-26'!B77 -> 36986.81 | H91: ='Jul-26'!B75 -> 37250.21 | I91: ='Ago-26'!B73 -> 39977.51 | J91: =SUM(B91:I91) -> 588414.32
A92: CPRB - ADM | B92: ='Jan-26'!B89 -> 124151.78 | J92: =SUM(B92:I92) -> 124151.78
A93: FGTS S/ FERIAS - ADM | B93: ='Jan-26'!B90 -> 25912.1 | C93: ='Fev-26'!B75 -> 1290.48 | D93: ='Mar-26'!B78 -> 1047.5 | E93: ='Abr-26'!B79 -> 1042.36 | F93: ='Mai-26'!B77 -> 1037.25 | G93: ='Jun-26'!B78 -> 1037.14 | H93: ='Jul-26'!B76 -> 1101.86 | I93: ='Ago-26'!B74 -> 1132.25 | J93: =SUM(B93:I93) -> 33600.94
A94: INSS S/ FERIAS - ADM | D94: ='Mar-26'!B79 -> 3923.68 | E94: ='Abr-26'!B80 -> 3917.87 | F94: ='Mai-26'!B78 -> 3901.08 | G94: ='Jun-26'!B79 -> 3900.64 | H94: ='Jul-26'!B77 -> 4121.37 | I94: ='Ago-26'!B75 -> 4228.21 | J94: =SUM(B94:I94) -> 23992.85
A95: INSS S/ DECIMO TERCEIRO SALARIO - ADM | B95: ='Jan-26'!B91 -> 12940.81 | C95: ='Fev-26'!B76 -> 3149.36 | D95: ='Mar-26'!B80 -> 3002.9 | E95: ='Abr-26'!B81 -> 2945.35 | F95: ='Mai-26'!B79 -> 2933.15 | G95: ='Jun-26'!B80 -> 2939.44 | H95: ='Jul-26'!B78 -> 3102.99 | I95: ='Ago-26'!B76 -> 3183.49 | J95: =SUM(B95:I95) -> 34197.49
A96: FGTS S/ DECIMO TERCEIRO SALARIO - ADM | B96: ='Jan-26'!B92 -> 11288.58 | C96: ='Fev-26'!B77 -> 843.1 | D96: ='Mar-26'!B81 -> 803.23 | E96: ='Abr-26'!B82 -> 783.61 | F96: ='Mai-26'!B80 -> 779.92 | G96: ='Jun-26'!B81 -> 781.61 | H96: ='Jul-26'!B79 -> 829.58 | I96: ='Ago-26'!B77 -> 852.47 | J96: =SUM(B96:I96) -> 16962.1
A97: GRRF - DESPESA RESCISORIA - ADM | B97: ='Jan-26'!B93 -> 187558.61 | C97: ='Fev-26'!B78 -> 25279.49 | D97: ='Mar-26'!B82 -> 18198.95 | E97: ='Abr-26'!B83 -> 23157.3 | G97: ='Jun-26'!B82 -> 20158.47 | H97: ='Jul-26'!B80 -> 3390.19 | I97: ='Ago-26'!B78 -> 11795.25 | J97: =SUM(B97:I97) -> 289538.26
A98: GASTOS PRODUCAO | B98: ='Jan-26'!B94 -> 11059817 | C98: ='Fev-26'!B79 -> 780868.27 | D98: ='Mar-26'!B83 -> 908031.19 | E98: ='Abr-26'!B84 -> 734917.44 | F98: ='Mai-26'!B81 -> 503630.72 | G98: ='Jun-26'!B83 -> 601270.45 | H98: ='Jul-26'!B81 -> 773805.81 | I98: ='Ago-26'!B79 -> 648158.32 | J98: =SUM(B98:I98) -> 16010499
A99: GASTOS GERAIS DE PRODUCAO | B99: ='Jan-26'!B95 -> 11059817 | C99: ='Fev-26'!B80 -> 780868.27 | D99: ='Mar-26'!B84 -> 908031.19 | E99: ='Abr-26'!B85 -> 734917.44 | F99: ='Mai-26'!B82 -> 503630.72 | G99: ='Jun-26'!B84 -> 601270.45 | H99: ='Jul-26'!B82 -> 773805.81 | I99: ='Ago-26'!B80 -> 648158.32 | J99: =SUM(B99:I99) -> 16010499
A100: SEGUROS DA FABRICA | B100: ='Jan-26'!B96 -> 149646.08 | C100: ='Fev-26'!B81 -> 14503.04 | D100: ='Mar-26'!B85 -> 14503.33 | E100: ='Abr-26'!B86 -> 52.56 | F100: ='Mai-26'!B83 -> 52.54 | J100: =SUM(B100:I100) -> 178757.55
A101: ENERGIA ELETRICA | B101: ='Jan-26'!B97 -> 480437.67 | C101: ='Fev-26'!B82 -> 26733.22 | D101: ='Mar-26'!B86 -> 40641.89 | E101: ='Abr-26'!B87 -> 47574.25 | F101: ='Mai-26'!B84 -> 44474.15 | G101: ='Jun-26'!B85 -> 40866.91 | H101: ='Jul-26'!B83 -> 43999.82 | I101: ='Ago-26'!B81 -> 48563.29 | J101: =SUM(B101:I101) -> 773291.2
...

Sheet Jan-26
A1: INDUSTRIA SCHUMACHER LTDA
A2: Demonstração do Resultado do Exercício (DRE)
A3: Período: 01/01/2026 a 31/01/2026 | Filial: CONSOLIDADO
A4: CNPJ: 04.589.817/0001-06
A5: Valores em R$ (reais). Fonte: relatório do sistema contábil (PDF), convertido sem alteração de valores.
A7: Conta | B7: Valor (R$)
A8: RECEITA OPERACIONAL BRUTA | B8: 65256171
A9: RECEITAS DE VENDAS | B9: 66077106
A10: VENDAS MERCADO INTERNO | B10: 66077106
A11: VENDA PROD. IND. EM OP. CONTA PROPRIA (RESULTADO) | B11: 36324920
A12: FATURAMENTO CFE. DL1598/77 ART.12 ITEM I | B12: 29520870
A13: VENDA DE SUCATA/ RESIDUO/ RECICLADOS | B13: 231315.75
A14: VENDAS MERCADO EXTERNO | B14: 7093786.6
A15: VENDA DESTINADA A EXPORTACAO | B15: 2527913.2
A16: EXPORTACAO PROPRIA | B16: 4475893.3
A17: VENDA PRA DRAWBACK | B17: 5265
A18: VENDA PROD. CONSIGNADO DEST. A EXPORTACAO | B18: 84715.1
A19: SERVIÇOS MERCADO INTERNO | B19: 3083029.6
... A187: LUCRO OU PREJUIZO LÍQUIDO DO EXERCÍCIO | B187: 3286063.3
A189: MARECHAL CANDIDO RONDON, 31 de janeiro de 2026
A191: ADAIR SCHUMACHER | B191: PAULO HENRIQUE DIAS RODRIGUES
A192: C.P.F. Nº 90348664915 | B192: C.R.C Nº CRC/DF 27618/O
A193: SOCIO GERENTE | B193: CONTADOR(A)

Sheet Fev-26
A1: INDUSTRIA SCHUMACHER LTDA
A2: Demonstração do Resultado do Exercício (DRE)
A3: Período: 01/02/2026 a 28/02/2026 | Filial: CONSOLIDADO
A4: CNPJ: 04.589.817/0001-06
A5: Valores em R$ (reais). Fonte: relatório do sistema contábil (PDF), convertido sem alteração de valores.
A7: Conta | B7: Valor (R$)
A8: RECEITA OPERACIONAL BRUTA | B8: 4421800.7
A9: RECEITAS DE VENDAS | B9: 4726850.5
A10: VENDAS MERCADO INTERNO | B10: 4726850.5
A11: VENDA PROD. IND. EM OP. CONTA PROPRIA (RESULTADO) | B11: 4710051
A12: VENDA DE SUCATA/ RESIDUO/ RECICLADOS | B12: 16799.41
A13: VENDAS MERCADO EXTERNO | B13: 211332.15
A14: VENDA DESTINADA A EXPORTACAO | B14: 199345.15
A15: EXPORTACAO PROPRIA | B15: 11987
A16: SERVIÇOS MERCADO INTERNO | B16: 189429.19
A17: INDUSTRIALIZACAO EFETUADA A TERCEIROS | B17: 152965.49
A18: PRESTACAO DE SERVICOS | B18: 36463.7
A19: (-) IMPOSTOS SOBRE VENDAS | B19: 705811.06
... A147: LUCRO OU PREJUIZO LÍQUIDO DO EXERCÍCIO | B147: -1242712.1
A149: MARECHAL CANDIDO RONDON, 28 de fevereiro de 2026
A151: ADAIR SCHUMACHER | B151: PAULO HENRIQUE DIAS RODRIGUES
A152: C.P.F. Nº 90348664915 | B152: C.R.C Nº CRC/DF 27618/O
A153: SOCIO GERENTE | B153: CONTADOR(A)

Sheet Mar-26
A1: INDUSTRIA SCHUMACHER LTDA
A2: Demonstração do Resultado do Exercício (DRE)
A3: Período: 01/03/2026 a 31/03/2026 | Filial: CONSOLIDADO
A4: CNPJ: 04.589.817/0001-06
A5: Valores em R$ (reais). Fonte: relatório do sistema contábil (PDF), convertido sem alteração de valores.
A7: Conta | B7: Valor (R$)
A8: RECEITA OPERACIONAL BRUTA | B8: 5895674.1
A9: RECEITAS DE VENDAS | B9: 6009654.5
A10: VENDAS MERCADO INTERNO | B10: 6009654.5
A11: VENDA PROD. IND. EM OP. CONTA PROPRIA (RESULTADO) | B11: 5991540.5
A12: VENDA DE SUCATA/ RESIDUO/ RECICLADOS | B12: 18114
A13: VENDAS MERCADO EXTERNO | B13: 714871.99
A14: VENDA DESTINADA A EXPORTACAO | B14: 185945.39
A15: EXPORTACAO PROPRIA | B15: 528926.6
A16: SERVIÇOS MERCADO INTERNO | B16: 292393.44
A17: INDUSTRIALIZACAO EFETUADA A TERCEIROS | B17: 168743.86
A18: PRESTACAO DE SERVICOS | B18: 123649.58
A19: (-) IMPOSTOS SOBRE VENDAS | B19: 1121245.9
... A157: LUCRO OU PREJUIZO LÍQUIDO DO EXERCÍCIO | B157: -2982381.6
A159: MARECHAL CANDIDO RONDON, 31 de março de 2026
A161: ADAIR SCHUMACHER | B161: PAULO HENRIQUE DIAS RODRIGUES
A162: C.P.F. Nº 90348664915 | B162: C.R.C Nº CRC/DF 27618/O
A163: SOCIO GERENTE | B163: CONTADOR(A)

Sheet Abr-26
A1: INDUSTRIA SCHUMACHER LTDA
A2: Demonstração do Resultado do Exercício (DRE)
A3: Período: 01/04/2026 a 30/04/2026 | Filial: CONSOLIDADO
A4: CNPJ: 04.589.817/0001-06
A5: Valores em R$ (reais). Fonte: relatório do sistema contábil (PDF), convertido sem alteração de valores.
A7: Conta | B7: Valor (R$)
A8: RECEITA OPERACIONAL BRUTA | B8: 4724378.4
A9: RECEITAS DE VENDAS | B9: 4736464.6
A10: VENDAS MERCADO INTERNO | B10: 4736464.6
A11: VENDA PROD. IND. EM OP. CONTA PROPRIA (RESULTADO) | B11: 4715511.1
A12: VENDA DE SUCATA/ RESIDUO/ RECICLADOS | B12: 20953.49
A13: VENDAS MERCADO EXTERNO | B13: 605033.01
A14: VENDA DESTINADA A EXPORTACAO | B14: 237498.65
A15: EXPORTACAO PROPRIA | B15: 367534.36
A16: SERVIÇOS MERCADO INTERNO | B16: 324413.42
A17: INDUSTRIALIZACAO EFETUADA A TERCEIROS | B17: 214665.07
A18: PRESTACAO DE SERVICOS | B18: 109748.35
A19: (-) IMPOSTOS SOBRE VENDAS | B19: 941532.59
... A155: LUCRO OU PREJUIZO LÍQUIDO DO EXERCÍCIO | B155: -1010496.9
A157: MARECHAL CANDIDO RONDON, 30 de abril de 2026
A159: ADAIR SCHUMACHER | B159: PAULO HENRIQUE DIAS RODRIGUES
A160: C.P.F. Nº 90348664915 | B160: C.R.C Nº CRC/DF 27618/O
A161: SOCIO GERENTE | B161: CONTADOR(A)

Sheet Mai-26
A1: INDUSTRIA SCHUMACHER LTDA
A2: Demonstração do Resultado do Exercício (DRE)
A3: Período: 01/05/2026 a 31/05/2026 | Filial: CONSOLIDADO
A4: CNPJ: 04.589.817/0001-06
A5: Valores em R$ (reais). Fonte: relatório do sistema contábil (PDF), convertido sem alteração de valores.
A7: Conta | B7: Valor (R$)
A8: RECEITA OPERACIONAL BRUTA | B8: 4982409
A9: RECEITAS DE VENDAS | B9: 4698899.2
A10: VENDAS MERCADO INTERNO | B10: 4698899.2
A11: VENDA PROD. IND. EM OP. CONTA PROPRIA (RESULTADO) | B11: 4682776.2
A12: VENDA DE SUCATA/ RESIDUO/ RECICLADOS | B12: 16123
A13: VENDAS MERCADO EXTERNO | B13: 720828.08
A14: VENDA DESTINADA A EXPORTACAO | B14: 104523.32
A15: EXPORTACAO PROPRIA | B15: 616304.76
A16: SERVIÇOS MERCADO INTERNO | B16: 323104.2
A17: INDUSTRIALIZACAO EFETUADA A TERCEIROS | B17: 194366.82
A18: PRESTACAO DE SERVICOS | B18: 128737.38
A19: (-) IMPOSTOS SOBRE VENDAS | B19: 760422.52
... A159: LUCRO OU PREJUIZO LÍQUIDO DO EXERCÍCIO | B159: -1117187.2
A161: MARECHAL CANDIDO RONDON, 31 de maio de 2026
A163: ADAIR SCHUMACHER | B163: PAULO HENRIQUE DIAS RODRIGUES
A164: C.P.F. Nº 90348664915 | B164: C.R.C Nº CRC/DF 27618/O
A165: SOCIO GERENTE | B165: CONTADOR(A)

Sheet Jun-26
A1: INDUSTRIA SCHUMACHER LTDA
A2: Demonstração do Resultado do Exercício (DRE)
A3: Período: 01/06/2026 a 30/06/2026 | Filial: CONSOLIDADO
A4: CNPJ: 04.589.817/0001-06
A5: Valores em R$ (reais). Fonte: relatório do sistema contábil (PDF), convertido sem alteração de valores.
A7: Conta | B7: Valor (R$)
A8: RECEITA OPERACIONAL BRUTA | B8: 5521005
A9: RECEITAS DE VENDAS | B9: 6249304.5
A10: VENDAS MERCADO INTERNO | B10: 6249304.5
A11: VENDA PROD. IND. EM OP. CONTA PROPRIA (RESULTADO) | B11: 6235791.5
A12: VENDA DE SUCATA/ RESIDUO/ RECICLADOS | B12: 13513
A13: VENDAS MERCADO EXTERNO | B13: 462652.85
A14: VENDA DESTINADA A EXPORTACAO | B14: 322203.11
A15: EXPORTACAO PROPRIA | B15: 140449.74
A16: SERVIÇOS MERCADO INTERNO | B16: 425153.82
A17: INDUSTRIALIZACAO EFETUADA A TERCEIROS | B17: 270329.01
A18: PRESTACAO DE SERVICOS | B18: 154824.81
A19: (-) IMPOSTOS SOBRE VENDAS | B19: 1616106.2
... A155: LUCRO OU PREJUIZO LÍQUIDO DO EXERCÍCIO | B155: -1131810.9
A157: MARECHAL CANDIDO RONDON, 30 de junho de 2026
A159: ADAIR SCHUMACHER | B159: PAULO HENRIQUE DIAS RODRIGUES
A160: C.P.F. Nº 90348664915 | B160: C.R.C Nº CRC/DF 27618/O
A161: SOCIO GERENTE | B161: CONTADOR(A)

Sheet Jul-26
A1: INDUSTRIA SCHUMACHER LTDA
A2: Demonstração do Resultado do Exercício (DRE)
A3: Período: 01/07/2026 a 31/07/2026 | Filial: CONSOLIDADO
A4: CNPJ: 04.589.817/0001-06
A5: Valores em R$ (reais). Fonte: relatório do sistema contábil (PDF), convertido sem alteração de valores.
A7: Conta | B7: Valor (R$)
A8: RECEITA OPERACIONAL BRUTA | B8: 5702251
A9: RECEITAS DE VENDAS | B9: 5895604.8
A10: VENDAS MERCADO INTERNO | B10: 5895604.8
A11: VENDA PROD. IND. EM OP. CONTA PROPRIA (RESULTADO) | B11: 5863520.3
A12: VENDA DE SUCATA/ RESIDUO/ RECICLADOS | B12: 32084.5
A13: VENDAS MERCADO EXTERNO | B13: 390744.11
A14: VENDA DESTINADA A EXPORTACAO | B14: 42378.34
A15: EXPORTACAO PROPRIA | B15: 348365.77
A16: SERVIÇOS MERCADO INTERNO | B16: 350984.55
A17: INDUSTRIALIZACAO EFETUADA A TERCEIROS | B17: 203764.46
A18: PRESTACAO DE SERVICOS | B18: 147220.09
A19: (-) IMPOSTOS SOBRE VENDAS | B19: 935082.47
... A150: LUCRO OU PREJUIZO LÍQUIDO DO EXERCÍCIO | B150: -512205.13
A152: MARECHAL CANDIDO RONDON, 31 de julho de 2026
A154: ADAIR SCHUMACHER | B154: PAULO HENRIQUE DIAS RODRIGUES
A155: C.P.F. Nº 90348664915 | B155: C.R.C Nº CRC/DF 27618/O
A156: SOCIO GERENTE | B156: CONTADOR(A)

Sheet Ago-26
A1: INDUSTRIA SCHUMACHER LTDA
A2: Demonstração do Resultado do Exercício (DRE)
A3: Período: 01/08/2026 a 31/08/2026 | Filial: CONSOLIDADO
A4: CNPJ: 04.589.817/0001-06
A5: Valores em R$ (reais). Fonte: relatório do sistema contábil (PDF), convertido sem alteração de valores.
A7: Conta | B7: Valor (R$)
A8: RECEITA OPERACIONAL BRUTA | B8: 5448307.6
A9: RECEITAS DE VENDAS | B9: 5683386
A10: VENDAS MERCADO INTERNO | B10: 5683386
A11: VENDA PROD. IND. EM OP. CONTA PROPRIA (RESULTADO) | B11: 5667516.5
A12: VENDA DE SUCATA/ RESIDUO/ RECICLADOS | B12: 15869.6
A13: VENDAS MERCADO EXTERNO | B13: 308252.92
A14: VENDA DESTINADA A EXPORTACAO | B14: 268734.72
A15: EXPORTACAO PROPRIA | B15: 39518.2
A16: SERVIÇOS MERCADO INTERNO | B16: 370038.22
A17: INDUSTRIALIZACAO EFETUADA A TERCEIROS | B17: 234613.03
A18: PRESTACAO DE SERVICOS | B18: 135425.19
A19: (-) IMPOSTOS SOBRE VENDAS | B19: 913369.58
... A152: LUCRO OU PREJUIZO LÍQUIDO DO EXERCÍCIO | B152: -60274.01
A154: MARECHAL CANDIDO RONDON, 31 de agosto de 2026
A156: ADAIR SCHUMACHER | B156: PAULO HENRIQUE DIAS RODRIGUES
A157: C.P.F. Nº 90348664915 | B157: C.R.C Nº CRC/DF 27618/O
A158: SOCIO GERENTE | B158: CONTADOR(A)
