Workbook

Sheet Resumo
A1: INDUSTRIA SCHUMACHER LTDA — Vendas por Produto 2026
A2: Resumo mensal: Matriz x Filial (SCHUMACHER SERVICOS) — valores puxados das abas de cada mês
B4: MATRIZ | G4: FILIAL | L4: CONSOLIDADO
A5: Mês | B5: Itens | C5: Total Vendas | D5: Custo | E5: Lucro Bruto | F5: Marg. Bruta | G5: Itens | H5: Total Vendas | I5: Custo | J5: Lucro Bruto | K5: Marg. Bruta | L5: Total Vendas | M5: Lucro Bruto | N5: Marg. Bruta
A6: 01 - Janeiro | B6: =COUNTA('Matriz 01'!A6:A249) -> 244 | C6: ='Matriz 01'!G250 -> 2124363.7 | D6: ='Matriz 01'!H250 -> 879028.75 | E6: ='Matriz 01'!I250 -> 1245335 | F6: =IFERROR(E6/C6,0) -> 0.58621553 | G6: =COUNTA('Filial 01'!A6:A58) -> 53 | H6: ='Filial 01'!G59 -> 731003.59 | I6: ='Filial 01'!H59 -> 562436.01 | J6: ='Filial 01'!I59 -> 168567.6 | K6: =IFERROR(J6/H6,0) -> 0.2305975 | L6: =C6+H6 -> 2855367.3 | M6: =E6+J6 -> 1413902.6 | N6: =IFERROR(M6/L6,0) -> 0.49517363
A7: 02 - Fevereiro | B7: =COUNTA('Matriz 02'!A6:A253) -> 248 | C7: ='Matriz 02'!G254 -> 3274708.6 | D7: ='Matriz 02'!H254 -> 1516738.6 | E7: ='Matriz 02'!I254 -> 1757970.1 | F7: =IFERROR(E7/C7,0) -> 0.53683252 | G7: =COUNTA('Filial 02'!A6:A78) -> 73 | H7: ='Filial 02'!G79 -> 1713419.5 | I7: ='Filial 02'!H79 -> 1901056 | J7: ='Filial 02'!I79 -> -187636.43 | K7: =IFERROR(J7/H7,0) -> -0.10950992 | L7: =C7+H7 -> 4988128.1 | M7: =E7+J7 -> 1570333.6 | N7: =IFERROR(M7/L7,0) -> 0.31481422
A8: 03 - Março | B8: =COUNTA('Matriz 03'!A6:A293) -> 288 | C8: ='Matriz 03'!G294 -> 5353921.5 | D8: ='Matriz 03'!H294 -> 2446819.5 | E8: ='Matriz 03'!I294 -> 2907102.1 | F8: =IFERROR(E8/C8,0) -> 0.54298556 | G8: =COUNTA('Filial 03'!A6:A82) -> 77 | H8: ='Filial 03'!G83 -> 1469497.9 | I8: ='Filial 03'!H83 -> 3423774.2 | J8: ='Filial 03'!I83 -> -1954276.3 | K8: =IFERROR(J8/H8,0) -> -1.3298938 | L8: =C8+H8 -> 6823419.5 | M8: =E8+J8 -> 952825.8 | N8: =IFERROR(M8/L8,0) -> 0.13964051
A9: 04 - Abril | B9: =COUNTA('Matriz 04'!A6:A273) -> 268 | C9: ='Matriz 04'!G274 -> 4283103.8 | D9: ='Matriz 04'!H274 -> 1845819.2 | E9: ='Matriz 04'!I274 -> 2437284.6 | F9: =IFERROR(E9/C9,0) -> 0.56904635 | G9: =COUNTA('Filial 04'!A6:A85) -> 80 | H9: ='Filial 04'!G86 -> 1218422.3 | I9: ='Filial 04'!H86 -> 1465342.2 | J9: ='Filial 04'!I86 -> -246919.78 | K9: =IFERROR(J9/H9,0) -> -0.20265533 | L9: =C9+H9 -> 5501526.1 | M9: =E9+J9 -> 2190364.8 | N9: =IFERROR(M9/L9,0) -> 0.39813767
A10: 05 - Maio | B10: =COUNTA('Matriz 05'!A6:A268) -> 263 | C10: ='Matriz 05'!G269 -> 4114584.2 | D10: ='Matriz 05'!H269 -> 1765162.8 | E10: ='Matriz 05'!I269 -> 2349421.5 | F10: =IFERROR(E10/C10,0) -> 0.57099851 | G10: =COUNTA('Filial 05'!A6:A75) -> 70 | H10: ='Filial 05'!G76 -> 1437890.9 | I10: ='Filial 05'!H76 -> 1792939.6 | J10: ='Filial 05'!I76 -> -355048.72 | K10: =IFERROR(J10/H10,0) -> -0.24692327 | L10: =C10+H10 -> 5552475.1 | M10: =E10+J10 -> 1994372.7 | N10: =IFERROR(M10/L10,0) -> 0.35918626
A11: 06 - Junho | B11: =COUNTA('Matriz 06'!A6:A278) -> 273 | C11: ='Matriz 06'!G279 -> 5435050.7 | D11: ='Matriz 06'!H279 -> 2281439.8 | E11: ='Matriz 06'!I279 -> 3153611 | F11: =IFERROR(E11/C11,0) -> 0.5802358 | G11: =COUNTA('Filial 06'!A6:A72) -> 67 | H11: ='Filial 06'!G73 -> 1476214.1 | I11: ='Filial 06'!H73 -> 1614364.4 | J11: ='Filial 06'!I73 -> -138150.15 | K11: =IFERROR(J11/H11,0) -> -0.093584085 | L11: =C11+H11 -> 6911264.9 | M11: =E11+J11 -> 3015460.8 | N11: =IFERROR(M11/L11,0) -> 0.43631099
A12: 07 - Julho | B12: =COUNTA('Matriz 07'!A6:A290) -> 285 | C12: ='Matriz 07'!G291 -> 5249190.4 | D12: ='Matriz 07'!H291 -> 2594338.5 | E12: ='Matriz 07'!I291 -> 2654852 | F12: =IFERROR(E12/C12,0) -> 0.50576409 | G12: =COUNTA('Filial 07'!A6:A75) -> 70 | H12: ='Filial 07'!G76 -> 1189291.3 | I12: ='Filial 07'!H76 -> 1018171.4 | J12: ='Filial 07'!I76 -> 171119.94 | K12: =IFERROR(J12/H12,0) -> 0.14388396 | L12: =C12+H12 -> 6438481.7 | M12: =E12+J12 -> 2825971.9 | N12: =IFERROR(M12/L12,0) -> 0.43891899
A13: 08 - Agosto | B13: =COUNTA('Matriz 08'!A6:A275) -> 270 | C13: ='Matriz 08'!G276 -> 4936458.7 | D13: ='Matriz 08'!H276 -> 2062446 | E13: ='Matriz 08'!I276 -> 2874012.9 | F13: =IFERROR(E13/C13,0) -> 0.58220134 | G13: =COUNTA('Filial 08'!A6:A69) -> 64 | H13: ='Filial 08'!G70 -> 1336203.1 | I13: ='Filial 08'!H70 -> 712345.39 | J13: ='Filial 08'!I70 -> 623857.83 | K13: =IFERROR(J13/H13,0) -> 0.46688846 | L13: =C13+H13 -> 6272661.8 | M13: =E13+J13 -> 3497870.7 | N13: =IFERROR(M13/L13,0) -> 0.55763737
A14: TOTAL 01-08 | B14: =SUM(B6:B13) -> 2139 | C14: =SUM(C6:C13) -> 34771382 | D14: =SUM(D6:D13) -> 15391793 | E14: =SUM(E6:E13) -> 19379589 | F14: =IFERROR(E14/C14,0) -> 0.55734308 | G14: =SUM(G6:G13) -> 554 | H14: =SUM(H6:H13) -> 10571943 | I14: =SUM(I6:I13) -> 12490429 | J14: =SUM(J6:J13) -> -1918486 | K14: =IFERROR(J14/H14,0) -> -0.18146957 | L14: =SUM(L6:L13) -> 45343324 | M14: =SUM(M6:M13) -> 17461103 | N14: =IFERROR(M14/L14,0) -> 0.38508652
A16: Obs.: "Itens" = produtos com venda no mês; margens = lucro ÷ total vendido. Em cada aba mensal, o TOTAL GERAL confere com o "Total Geral" do PDF original.

Sheet Matriz 01
A1: INDUSTRIA SCHUMACHER LTDA — Matriz
A2: Demonstrativo de Margens de Venda por Produto
A3: Período: 01/01/2026 a 31/01/2026 (Janeiro/2026)
A5: Código | B5: Produto | C5: Qtde | D5: Qtde Un. | E5: A Vista | F5: A Prazo | G5: Total | H5: Custo | I5: Lucro Bruto | J5: Lucro Líquido | K5: Marg. Bruta | L5: Marg. Líquida | M5: PMP
A6: 10001 | B6: CILINDRO PNEUMATICO PARA BLOQUEIO | C6: 603 | D6: 603 | E6: 36.5 | F6: 17492.83 | G6: 17529.33 | H6: 7590.0271 | I6: 9939.3 | J6: 5162.28 | K6: 0.567 | L6: 0.2945 | M6: 43.12
A7: 10002 | B7: CONJUNTO VALVULA EVACUACAO SANITARIO | C7: 160 | D7: 160 | E7: 0 | F7: 52604.21 | G7: 52604.21 | H7: 13686.38 | I7: 38917.83 | J7: 25161.31 | K7: 0.7398 | L7: 0.4783 | M7: 45.78
A8: 10004 | B8: CONJUNTO CONTROLE DETERGENTE | C8: 2 | D8: 2 | E8: 0 | F8: 198 | G8: 198 | H8: 96.47 | I8: 101.53 | J8: 47.14 | K8: 0.5128 | L8: 0.2381 | M8: 60
A9: 10005 | B9: BOMBA DOSADORA BACTERICIDA | C9: 193 | D9: 193 | E9: 0 | F9: 21084.72 | G9: 21084.72 | H9: 2557.872 | I9: 18526.85 | J9: 13754.05 | K9: 0.8787 | L9: 0.6523 | M9: 36.19
A10: 10006 | B10: VALVULA DE RETENCAO | C10: 22 | D10: 22 | E10: 0 | F10: 1661.4 | G10: 1661.4 | H10: 171.6797 | I10: 1489.72 | J10: 1033.29 | K10: 0.8967 | L10: 0.6219 | M10: 48.73
A11: 10007 | B11: CONJUNTO VALVULA EVACUACAO SANITARIO | C11: 194 | D11: 194 | E11: 0 | F11: 63145.53 | G11: 63145.53 | H11: 17197.55 | I11: 45947.98 | J11: 29472.68 | K11: 0.7277 | L11: 0.4667 | M11: 52.96
A12: 10008 | B12: VALVULA DE CALEFACAO 24V | C12: 1372 | D12: 1372 | E12: 0 | F12: 234333.18 | G12: 234333.18 | H12: 86945.456 | I12: 147387.73 | J12: 93853.55 | K12: 0.629 | L12: 0.4005 | M12: 46.03
A13: 10011 | B13: CONJUNTO BOMBA SANITARIO | C13: 3 | D13: 3 | E13: 0 | F13: 441 | G13: 441 | H13: 149.4099 | I13: 291.59 | J13: 170.44 | K13: 0.6612 | L13: 0.3865 | M13: 50
A14: 10018 | B14: VALVULA DE RETENCAO | C14: 3 | D14: 3 | E14: 0 | F14: 282.47 | G14: 282.47 | H14: 100.47 | I14: 182 | J14: 118.01 | K14: 0.6443 | L14: 0.4178 | M14: 71.52
A15: 10021 | B15: CONJUNTO VALVULA EVACUACAO CAIXA DETRITO DD | C15: 20 | D15: 20 | E15: 0 | F15: 8345.4 | G15: 8345.4 | H15: 1620.56 | I15: 6724.84 | J15: 4432.2 | K15: 0.8058 | L15: 0.5311 | M15: 38
A16: 10022 | B16: CONJUNTO VALVULA EVACUACAO CAIXA DETRITO | C16: 21 | D16: 21 | E16: 0 | F16: 9616.68 | G16: 9616.68 | H16: 1685.66 | I16: 7931.02 | J16: 5306.29 | K16: 0.8247 | L16: 0.5518 | M16: 38.82
A17: 10024 | B17: DOBRADICA ASSENTO SANITARIO | C17: 110 | D17: 110 | E17: 0 | F17: 5308.6 | G17: 5308.6 | H17: 826.138 | I17: 4482.46 | J17: 3024.08 | K17: 0.8444 | L17: 0.5697 | M17: 50
... A249: 90632 | B249: CAIXA BALANCA | C249: 10 | D249: 10 | E249: 0 | F249: 3140 | G249: 3140 | H249: 1326.27 | I249: 1813.73 | J249: 1102.37 | K249: 0.5776 | L249: 0.3511 | M249: 16
A250: TOTAL GERAL | B250: =COUNTA(A6:A249)&" produtos" -> 244 produtos | C250: =SUM(C6:C249) -> 24481 | D250: =SUM(D6:D249) -> 24481 | E250: =SUM(E6:E249) -> 412.05 | F250: =SUM(F6:F249) -> 2123951.6 | G250: =SUM(G6:G249) -> 2124363.7 | H250: =SUM(H6:H249) -> 879028.75 | I250: =SUM(I6:I249) -> 1245335 | J250: =SUM(J6:J249) -> 733690.16 | K250: =IFERROR(I250/G250,0) -> 0.58621553 | L250: =IFERROR(J250/G250,0) -> 0.34536937 | M250: =IFERROR(SUMPRODUCT(M6:M249,G6:G249)/G250,0) -> 43.083953

Sheet Matriz 02
A1: INDUSTRIA SCHUMACHER LTDA — Matriz
A2: Demonstrativo de Margens de Venda por Produto
A3: Período: 01/02/2026 a 28/02/2026 (Fevereiro/2026)
A5: Código | B5: Produto | C5: Qtde | D5: Qtde Un. | E5: A Vista | F5: A Prazo | G5: Total | H5: Custo | I5: Lucro Bruto | J5: Lucro Líquido | K5: Marg. Bruta | L5: Marg. Líquida | M5: PMP
A6: 10001 | B6: CILINDRO PNEUMATICO PARA BLOQUEIO | C6: 1542 | D6: 1542 | E6: 1925 | F6: 47838.89 | G6: 49763.89 | H6: 21285.329 | I6: 28478.57 | J6: 15048.63 | K6: 0.5723 | L6: 0.3024 | M6: 39.98
A7: 10002 | B7: CONJUNTO VALVULA EVACUACAO SANITARIO | C7: 163 | D7: 163 | E7: 0 | F7: 49106.88 | G7: 49106.88 | H7: 12833.2 | I7: 36273.68 | J7: 25965.33 | K7: 0.7387 | L7: 0.5288 | M7: 37.49
A8: 10004 | B8: CONJUNTO CONTROLE DETERGENTE | C8: 2 | D8: 2 | E8: 0 | F8: 116.88 | G8: 116.88 | H8: 92.22 | I8: 24.66 | J8: -7.45 | K8: 0.211 | L8: -0.0637 | M8: 50
A9: 10005 | B9: BOMBA DOSADORA BACTERICIDA | C9: 470 | D9: 470 | E9: 0 | F9: 44610.09 | G9: 44610.09 | H9: 5959.774 | I9: 38650.32 | J9: 28142.17 | K9: 0.8664 | L9: 0.6308 | M9: 46.76
A10: 10006 | B10: VALVULA DE RETENCAO | C10: 6 | D10: 6 | E10: 66.96 | F10: 301.3 | G10: 368.26 | H10: 46.1401 | I10: 322.12 | J10: 226.75 | K10: 0.8747 | L10: 0.6157 | M10: 33.02
A11: 10007 | B11: CONJUNTO VALVULA EVACUACAO SANITARIO | C11: 243 | D11: 243 | E11: 0 | F11: 73276.93 | G11: 73276.93 | H11: 20464.529 | I11: 52812.4 | J11: 35074.48 | K11: 0.7207 | L11: 0.4787 | M11: 52.53
A12: 10008 | B12: VALVULA DE CALEFACAO 24V | C12: 1240 | D12: 1240 | E12: 0 | F12: 201569.93 | G12: 201569.93 | H12: 78296.398 | I12: 123273.54 | J12: 77003.58 | K12: 0.6116 | L12: 0.382 | M12: 49.87
A13: 10018 | B13: VALVULA DE RETENCAO | C13: 6 | D13: 6 | E13: 0 | F13: 479.22 | G13: 479.22 | H13: 199.56 | I13: 279.66 | J13: 171.1 | K13: 0.5836 | L13: 0.357 | M13: 50
A14: 10021 | B14: CONJUNTO VALVULA EVACUACAO CAIXA DETRITO DD | C14: 36 | D14: 36 | E14: 0 | F14: 15021.72 | G14: 15021.72 | H14: 2784.25 | I14: 12237.47 | J14: 8110.71 | K14: 0.8147 | L14: 0.5399 | M14: 44.67
A15: 10022 | B15: CONJUNTO VALVULA EVACUACAO CAIXA DETRITO | C15: 36 | D15: 36 | E15: 0 | F15: 15088.52 | G15: 15088.52 | H15: 2882.85 | I15: 12205.67 | J15: 8060.56 | K15: 0.8089 | L15: 0.5342 | M15: 37
A16: 10024 | B16: DOBRADICA ASSENTO SANITARIO | C16: 202 | D16: 202 | E16: 0 | F16: 9845.02 | G16: 9845.02 | H16: 1511.506 | I16: 8333.51 | J16: 5628.89 | K16: 0.8465 | L16: 0.5717 | M16: 47.94
A17: 10025 | B17: REPARO VALVULA EVACUACAO | C17: 10 | D17: 10 | E17: 0 | F17: 587.8 | G17: 587.8 | H17: 72.48 | I17: 515.32 | J17: 353.84 | K17: 0.8767 | L17: 0.602 | M17: 60
... A253: 90726 | B253: CONJ. CARRINHO PULVERIZADOR | C253: 1 | D253: 1 | E253: 0 | F253: 500 | G253: 500 | H253: 0 | I253: 500 | J253: 500 | K253: 1 | L253: 1 | M253: 30
A254: TOTAL GERAL | B254: =COUNTA(A6:A253)&" produtos" -> 248 produtos | C254: =SUM(C6:C253) -> 25277 | D254: =SUM(D6:D253) -> 25277 | E254: =SUM(E6:E253) -> 7898.88 | F254: =SUM(F6:F253) -> 3266809.7 | G254: =SUM(G6:G253) -> 3274708.6 | H254: =SUM(H6:H253) -> 1516738.6 | I254: =SUM(I6:I253) -> 1757970.1 | J254: =SUM(J6:J253) -> 888420.93 | K254: =IFERROR(I254/G254,0) -> 0.53683252 | L254: =IFERROR(J254/G254,0) -> 0.27129771 | M254: =IFERROR(SUMPRODUCT(M6:M253,G6:G253)/G254,0) -> 60.770875

Sheet Matriz 03
A1: INDUSTRIA SCHUMACHER LTDA — Matriz
A2: Demonstrativo de Margens de Venda por Produto
A3: Período: 01/03/2026 a 31/03/2026 (Março/2026)
A5: Código | B5: Produto | C5: Qtde | D5: Qtde Un. | E5: A Vista | F5: A Prazo | G5: Total | H5: Custo | I5: Lucro Bruto | J5: Lucro Líquido | K5: Marg. Bruta | L5: Marg. Líquida | M5: PMP
A6: 10001 | B6: CILINDRO PNEUMATICO PARA BLOQUEIO | C6: 1081 | D6: 1081 | E6: 845.34 | F6: 31229.95 | G6: 32075.29 | H6: 14711.718 | I6: 17363.57 | J6: 9016.94 | K6: 0.5413 | L6: 0.2811 | M6: 47.01
A7: 10002 | B7: CONJUNTO VALVULA EVACUACAO SANITARIO | C7: 191 | D7: 191 | E7: 1324.67 | F7: 60166.18 | G7: 61490.85 | H7: 16008.621 | I7: 45482.23 | J7: 29081.05 | K7: 0.7397 | L7: 0.4729 | M7: 46.21
A8: 10004 | B8: CONJUNTO CONTROLE DETERGENTE | C8: 2 | D8: 2 | E8: 0 | F8: 198 | G8: 198 | H8: 96.45 | I8: 101.55 | J8: 47.15 | K8: 0.5129 | L8: 0.2381 | M8: 60
A9: 10005 | B9: BOMBA DOSADORA BACTERICIDA | C9: 568 | D9: 568 | E9: 1635.01 | F9: 52172.88 | G9: 53807.89 | H9: 7116.674 | I9: 46691.22 | J9: 33389.69 | K9: 0.8677 | L9: 0.6205 | M9: 45.48
A10: 10006 | B10: VALVULA DE RETENCAO | C10: 45 | D10: 45 | E10: 258.47 | F10: 2830.68 | G10: 3089.15 | H10: 375.9603 | I10: 2713.19 | J10: 1883.05 | K10: 0.8783 | L10: 0.6096 | M10: 36.3
A11: 10007 | B11: CONJUNTO VALVULA EVACUACAO SANITARIO | C11: 268 | D11: 268 | E11: 2433.14 | F11: 82303.67 | G11: 84736.81 | H11: 22664.492 | I11: 62072.32 | J11: 39680.22 | K11: 0.7325 | L11: 0.4683 | M11: 47.78
A12: 10008 | B12: VALVULA DE CALEFACAO 24V | C12: 2349 | D12: 2349 | E12: 1226.79 | F12: 392592.1 | G12: 393818.89 | H12: 149031.01 | I12: 244787.88 | J12: 142399.36 | K12: 0.6216 | L12: 0.3616 | M12: 51.69
A13: 10018 | B13: VALVULA DE RETENCAO | C13: 6 | D13: 6 | E13: 0 | F13: 513.12 | G13: 513.12 | H13: 196.8 | I13: 316.32 | J13: 186.9 | K13: 0.6165 | L13: 0.3642 | M13: 27.08
A14: 10019 | B14: CONJUNTO VALVULA EVACUACAO SANITARIO | C14: 3 | D14: 3 | E14: 0 | F14: 930.9 | G14: 930.9 | H14: 216.57 | I14: 714.33 | J14: 472.51 | K14: 0.7674 | L14: 0.5076 | M14: 43.55
A15: 10021 | B15: CONJUNTO VALVULA EVACUACAO CAIXA DETRITO DD | C15: 11 | D15: 11 | E15: 0 | F15: 4481.56 | G15: 4481.56 | H15: 841.51 | I15: 3640.05 | J15: 2423.76 | K15: 0.8122 | L15: 0.5408 | M15: 41.97
A16: 10022 | B16: CONJUNTO VALVULA EVACUACAO CAIXA DETRITO | C16: 4 | D16: 4 | E16: 0 | F16: 1240 | G16: 1240 | H16: 322.93 | I16: 917.07 | J16: 576.41 | K16: 0.7396 | L16: 0.4648 | M16: 7
A17: 10024 | B17: DOBRADICA ASSENTO SANITARIO | C17: 120 | D17: 120 | E17: 0 | F17: 5791.2 | G17: 5791.2 | H17: 899.124 | I17: 4892.08 | J17: 3301.12 | K17: 0.8447 | L17: 0.57 | M17: 50
... A293: 90663 | B293: CONJ. SANITARIO COMPACTO | C293: 7 | D293: 7 | E293: 0 | F293: 102000 | G293: 102000 | H293: 67445.04 | I293: 34554.96 | J293: -837.25 | K293: 0.3388 | L293: -0.0082 | M293: 174.65
A294: TOTAL GERAL | B294: =COUNTA(A6:A293)&" produtos" -> 288 produtos | C294: =SUM(C6:C293) -> 50148 | D294: =SUM(D6:D293) -> 50148 | E294: =SUM(E6:E293) -> 56145.62 | F294: =SUM(F6:F293) -> 5297775.9 | G294: =SUM(G6:G293) -> 5353921.5 | H294: =SUM(H6:H293) -> 2446819.5 | I294: =SUM(I6:I293) -> 2907102.1 | J294: =SUM(J6:J293) -> 1566461.5 | K294: =IFERROR(I294/G294,0) -> 0.54298556 | L294: =IFERROR(J294/G294,0) -> 0.29258209 | M294: =IFERROR(SUMPRODUCT(M6:M293,G6:G293)/G294,0) -> 48.852139

Sheet Matriz 04
A1: INDUSTRIA SCHUMACHER LTDA — Matriz
A2: Demonstrativo de Margens de Venda por Produto
A3: Período: 01/04/2026 a 30/04/2026 (Abril/2026)
A5: Código | B5: Produto | C5: Qtde | D5: Qtde Un. | E5: A Vista | F5: A Prazo | G5: Total | H5: Custo | I5: Lucro Bruto | J5: Lucro Líquido | K5: Marg. Bruta | L5: Marg. Líquida | M5: PMP
A6: 10001 | B6: CILINDRO PNEUMATICO PARA BLOQUEIO | C6: 1089 | D6: 1089 | E6: 0 | F6: 32472.94 | G6: 32472.94 | H6: 15569.35 | I6: 16903.6 | J6: 8366.78 | K6: 0.5205 | L6: 0.2577 | M6: 49.49
A7: 10002 | B7: CONJUNTO VALVULA EVACUACAO SANITARIO | C7: 169 | D7: 169 | E7: 0 | F7: 54819.97 | G7: 54819.97 | H7: 13836.16 | I7: 40983.81 | J7: 26161.09 | K7: 0.7476 | L7: 0.4772 | M7: 50.99
A8: 10004 | B8: CONJUNTO CONTROLE DETERGENTE | C8: 4 | D8: 4 | E8: 0 | F8: 373.32 | G8: 373.32 | H8: 192.9 | I8: 180.42 | J8: 77.85 | K8: 0.4833 | L8: 0.2085 | M8: 54.77
A9: 10005 | B9: BOMBA DOSADORA BACTERICIDA | C9: 582 | D9: 582 | E9: 0 | F9: 54459.52 | G9: 54459.52 | H9: 7309.2087 | I9: 47150.31 | J9: 33328.31 | K9: 0.8658 | L9: 0.612 | M9: 44.93
A10: 10006 | B10: VALVULA DE RETENCAO | C10: 5 | D10: 5 | E10: 0 | F10: 329.94 | G10: 329.94 | H10: 41.7801 | I10: 288.16 | J10: 197.52 | K10: 0.8734 | L10: 0.5987 | M10: 60
A11: 10007 | B11: CONJUNTO VALVULA EVACUACAO SANITARIO | C11: 230 | D11: 230 | E11: 0 | F11: 71073.4 | G11: 71073.4 | H11: 19165.67 | I11: 51907.73 | J11: 33412.04 | K11: 0.7303 | L11: 0.4701 | M11: 49.6
A12: 10008 | B12: VALVULA DE CALEFACAO 24V | C12: 1988 | D12: 1988 | E12: 0 | F12: 328222.36 | G12: 328222.36 | H12: 126710.11 | I12: 201512.25 | J12: 125686.75 | K12: 0.614 | L12: 0.3829 | M12: 45.9
A13: 10012 | B13: VALVULA DE RETENCAO CINZA | C13: 1 | D13: 1 | E13: 0 | F13: 60.26 | G13: 60.26 | H13: 8.72 | I13: 51.54 | J13: 37.89 | K13: 0.8553 | L13: 0.6288 | M13: 7
A14: 10018 | B14: VALVULA DE RETENCAO | C14: 1 | D14: 1 | E14: 0 | F14: 79.87 | G14: 79.87 | H14: 33.07 | I14: 46.8 | J14: 28.71 | K14: 0.586 | L14: 0.3595 | M14: 50
A15: 10019 | B15: CONJUNTO VALVULA EVACUACAO SANITARIO | C15: 1 | D15: 1 | E15: 0 | F15: 288.9 | G15: 288.9 | H15: 70.56 | I15: 218.34 | J15: 152.89 | K15: 0.7558 | L15: 0.5292 | M15: 7
A16: 10021 | B16: CONJUNTO VALVULA EVACUACAO CAIXA DETRITO DD | C16: 30 | D16: 30 | E16: 0 | F16: 10006.7 | G16: 10006.7 | H16: 2221.5 | I16: 7785.2 | J16: 5923.63 | K16: 0.778 | L16: 0.592 | M16: 34.63
A17: 10022 | B17: CONJUNTO VALVULA EVACUACAO CAIXA DETRITO | C17: 8 | D17: 8 | E17: 0 | F17: 2837.14 | G17: 2837.14 | H17: 627.0701 | I17: 2210.07 | J17: 1498.69 | K17: 0.779 | L17: 0.5282 | M17: 53.8
... A273: 90739 | B273: CAIXA JUNCAO | C273: 20 | D273: 20 | E273: 0 | F273: 6180 | G273: 6180 | H273: 2442.36 | I273: 3737.64 | J273: 2039.88 | K273: 0.6048 | L273: 0.3301 | M273: 60
A274: TOTAL GERAL | B274: =COUNTA(A6:A273)&" produtos" -> 268 produtos | C274: =SUM(C6:C273) -> 52382 | D274: =SUM(D6:D273) -> 52382 | E274: =SUM(E6:E273) -> 1082.11 | F274: =SUM(F6:F273) -> 4282021.7 | G274: =SUM(G6:G273) -> 4283103.8 | H274: =SUM(H6:H273) -> 1845819.2 | I274: =SUM(I6:I273) -> 2437284.6 | J274: =SUM(J6:J273) -> 1383237.2 | K274: =IFERROR(I274/G274,0) -> 0.56904635 | L274: =IFERROR(J274/G274,0) -> 0.32295207 | M274: =IFERROR(SUMPRODUCT(M6:M273,G6:G273)/G274,0) -> 47.895521

Sheet Matriz 05
A1: INDUSTRIA SCHUMACHER LTDA — Matriz
A2: Demonstrativo de Margens de Venda por Produto
A3: Período: 01/05/2026 a 31/05/2026 (Maio/2026)
A5: Código | B5: Produto | C5: Qtde | D5: Qtde Un. | E5: A Vista | F5: A Prazo | G5: Total | H5: Custo | I5: Lucro Bruto | J5: Lucro Líquido | K5: Marg. Bruta | L5: Marg. Líquida | M5: PMP
A6: 10001 | B6: CILINDRO PNEUMATICO PARA BLOQUEIO | C6: 990 | D6: 990 | E6: 146 | F6: 30955.95 | G6: 31101.95 | H6: 14324.215 | I6: 16777.74 | J6: 8468.15 | K6: 0.5394 | L6: 0.2723 | M6: 45.56
A7: 10002 | B7: CONJUNTO VALVULA EVACUACAO SANITARIO | C7: 172 | D7: 172 | E7: 446.13 | F7: 55482.65 | G7: 55928.78 | H7: 15044.641 | I7: 40884.14 | J7: 25569.83 | K7: 0.731 | L7: 0.4572 | M7: 46.05
A8: 10004 | B8: CONJUNTO CONTROLE DETERGENTE | C8: 4 | D8: 4 | E8: 0 | F8: 396 | G8: 396 | H8: 192.91 | I8: 203.09 | J8: 113.38 | K8: 0.5129 | L8: 0.2863 | M8: 60
A9: 10005 | B9: BOMBA DOSADORA BACTERICIDA | C9: 644 | D9: 644 | E9: 0 | F9: 60428.98 | G9: 60428.98 | H9: 8286.7489 | I9: 52142.23 | J9: 37950.67 | K9: 0.8629 | L9: 0.628 | M9: 42.29
A10: 10006 | B10: VALVULA DE RETENCAO | C10: 10 | D10: 10 | E10: 0 | F10: 800.24 | G10: 800.24 | H10: 98.34 | I10: 701.9 | J10: 482.05 | K10: 0.8771 | L10: 0.6024 | M10: 42.53
A11: 10007 | B11: CONJUNTO VALVULA EVACUACAO SANITARIO | C11: 256 | D11: 256 | E11: 686.36 | F11: 76368.9 | G11: 77055.26 | H11: 21545.112 | I11: 55510.15 | J11: 38015.46 | K11: 0.7204 | L11: 0.4934 | M11: 40.66
A12: 10008 | B12: VALVULA DE CALEFACAO 24V | C12: 1305 | D12: 1305 | E12: 5085.12 | F12: 221595.12 | G12: 226680.24 | H12: 84512.188 | I12: 142168.06 | J12: 90213.25 | K12: 0.6272 | L12: 0.398 | M12: 42.66
A13: 10012 | B13: VALVULA DE RETENCAO CINZA | C13: 2 | D13: 2 | E13: 0 | F13: 172.7 | G13: 172.7 | H13: 20.8 | I13: 151.9 | J13: 104.46 | K13: 0.8796 | L13: 0.6049 | M13: 7
A14: 10018 | B14: VALVULA DE RETENCAO | C14: 14 | D14: 14 | E14: 0 | F14: 1263.66 | G14: 1263.66 | H14: 472.68 | I14: 790.98 | J14: 491.04 | K14: 0.6259 | L14: 0.3886 | M14: 45.89
A15: 10019 | B15: CONJUNTO VALVULA EVACUACAO SANITARIO | C15: 11 | D15: 11 | E15: 0 | F15: 3017.4 | G15: 3017.4 | H15: 830.2 | I15: 2187.2 | J15: 1787.23 | K15: 0.7249 | L15: 0.5923 | M15: 54.93
A16: 10021 | B16: CONJUNTO VALVULA EVACUACAO CAIXA DETRITO DD | C16: 8 | D16: 8 | E16: 0 | F16: 3338.16 | G16: 3338.16 | H16: 615.11 | I16: 2723.05 | J16: 1805.99 | K16: 0.8157 | L16: 0.541 | M16: 45
A17: 10022 | B17: CONJUNTO VALVULA EVACUACAO CAIXA DETRITO | C17: 14 | D17: 14 | E17: 0 | F17: 5140.71 | G17: 5140.71 | H17: 1129.11 | I17: 4011.6 | J17: 2599.33 | K17: 0.7804 | L17: 0.5056 | M17: 43.11
... A268: 90742 | B268: CAIXA JUNCAO | C268: 1 | D268: 1 | E268: 0 | F268: 359.56 | G268: 359.56 | H268: 129.5 | I268: 230.06 | J268: 148.6 | K268: 0.6398 | L268: 0.4133 | M268: 5
A269: TOTAL GERAL | B269: =COUNTA(A6:A268)&" produtos" -> 263 produtos | C269: =SUM(C6:C268) -> 52985.5 | D269: =SUM(D6:D268) -> 52985.5 | E269: =SUM(E6:E268) -> 51910.38 | F269: =SUM(F6:F268) -> 4062673.9 | G269: =SUM(G6:G268) -> 4114584.2 | H269: =SUM(H6:H268) -> 1765162.8 | I269: =SUM(I6:I268) -> 2349421.5 | J269: =SUM(J6:J268) -> 1342882.9 | K269: =IFERROR(I269/G269,0) -> 0.57099851 | L269: =IFERROR(J269/G269,0) -> 0.32637147 | M269: =IFERROR(SUMPRODUCT(M6:M268,G6:G268)/G269,0) -> 40.291894

Sheet Matriz 06
A1: INDUSTRIA SCHUMACHER LTDA — Matriz
A2: Demonstrativo de Margens de Venda por Produto
A3: Período: 01/06/2026 a 30/06/2026 (Junho/2026)
A5: Código | B5: Produto | C5: Qtde | D5: Qtde Un. | E5: A Vista | F5: A Prazo | G5: Total | H5: Custo | I5: Lucro Bruto | J5: Lucro Líquido | K5: Marg. Bruta | L5: Marg. Líquida | M5: PMP
A6: 10001 | B6: CILINDRO PNEUMATICO PARA BLOQUEIO | C6: 1050 | D6: 1050 | E6: 0 | F6: 31478.94 | G6: 31478.94 | H6: 13700.855 | I6: 17778.08 | J6: 9077.59 | K6: 0.5648 | L6: 0.2884 | M6: 41.42
A7: 10002 | B7: CONJUNTO VALVULA EVACUACAO SANITARIO | C7: 252 | D7: 252 | E7: 0 | F7: 80080.74 | G7: 80080.74 | H7: 22117.428 | I7: 57963.31 | J7: 37002.75 | K7: 0.7238 | L7: 0.4621 | M7: 50.72
A8: 10004 | B8: CONJUNTO CONTROLE DETERGENTE | C8: 1 | D8: 1 | E8: 0 | F8: 99 | G8: 99 | H8: 48.23 | I8: 50.77 | J8: 23.58 | K8: 0.5128 | L8: 0.2382 | M8: 30
A9: 10005 | B9: BOMBA DOSADORA BACTERICIDA | C9: 759 | D9: 759 | E9: 0 | F9: 71089.1 | G9: 71089.1 | H9: 9987.747 | I9: 61101.35 | J9: 43964.55 | K9: 0.8595 | L9: 0.6184 | M9: 51.65
A10: 10006 | B10: VALVULA DE RETENCAO | C10: 27 | D10: 27 | E10: 0 | F10: 1662.82 | G10: 1662.82 | H10: 267.7996 | I10: 1395.02 | J10: 952.72 | K10: 0.8389 | L10: 0.573 | M10: 40.28
A11: 10007 | B11: CONJUNTO VALVULA EVACUACAO SANITARIO | C11: 309 | D11: 309 | E11: 0 | F11: 93443.36 | G11: 93443.36 | H11: 26698.921 | I11: 66744.44 | J11: 43661.86 | K11: 0.7143 | L11: 0.4673 | M11: 50.9
A12: 10008 | B12: VALVULA DE CALEFACAO 24V | C12: 1342 | D12: 1342 | E12: 1483.16 | F12: 241344.14 | G12: 242827.3 | H12: 89386.246 | I12: 153441.06 | J12: 93930.75 | K12: 0.6319 | L12: 0.3868 | M12: 54.3
A13: 10012 | B13: VALVULA DE RETENCAO CINZA | C13: 1 | D13: 1 | E13: 0 | F13: 66.96 | G13: 66.96 | H13: 10.4 | I13: 56.56 | J13: 38.17 | K13: 0.8447 | L13: 0.57 | M13: 45
A14: 10018 | B14: VALVULA DE RETENCAO | C14: 16 | D14: 16 | E14: 0 | F14: 1530.75 | G14: 1530.75 | H14: 551.31 | I14: 979.44 | J14: 555.53 | K14: 0.6398 | L14: 0.3629 | M14: 41.82
A15: 10021 | B15: CONJUNTO VALVULA EVACUACAO CAIXA DETRITO DD | C15: 11 | D15: 11 | E15: 0 | F15: 4589.97 | G15: 4589.97 | H15: 838.84 | I15: 3751.13 | J15: 2490.17 | K15: 0.8172 | L15: 0.5425 | M15: 44.18
A16: 10022 | B16: CONJUNTO VALVULA EVACUACAO CAIXA DETRITO | C16: 9 | D16: 9 | E16: 0 | F16: 3035.58 | G16: 3035.58 | H16: 729.01 | I16: 2306.57 | J16: 1472.64 | K16: 0.7598 | L16: 0.4851 | M16: 25.77
A17: 10024 | B17: DOBRADICA ASSENTO SANITARIO | C17: 270 | D17: 270 | E17: 0 | F17: 13030.2 | G17: 13030.2 | H17: 1986.698 | I17: 11043.5 | J17: 7463.87 | K17: 0.8475 | L17: 0.5728 | M17: 50
... A278: 90691 | B278: PECA PERSONALIZADA INOX | C278: 11 | D278: 11 | E278: 0 | F278: 13327.2 | G278: 13327.2 | H278: 0 | I278: 13327.2 | J278: 13327.2 | K278: 1 | L278: 1 | M278: 44.2
A279: TOTAL GERAL | B279: =COUNTA(A6:A278)&" produtos" -> 273 produtos | C279: =SUM(C6:C278) -> 66919 | D279: =SUM(D6:D278) -> 66919 | E279: =SUM(E6:E278) -> 5276.89 | F279: =SUM(F6:F278) -> 5429773.8 | G279: =SUM(G6:G278) -> 5435050.7 | H279: =SUM(H6:H278) -> 2281439.8 | I279: =SUM(I6:I278) -> 3153611 | J279: =SUM(J6:J278) -> 1697471.4 | K279: =IFERROR(I279/G279,0) -> 0.5802358 | L279: =IFERROR(J279/G279,0) -> 0.31231932 | M279: =IFERROR(SUMPRODUCT(M6:M278,G6:G278)/G279,0) -> 59.851416

Sheet Matriz 07
A1: INDUSTRIA SCHUMACHER LTDA — Matriz
A2: Demonstrativo de Margens de Venda por Produto
A3: Período: 01/07/2026 a 31/07/2026 (Julho/2026)
A5: Código | B5: Produto | C5: Qtde | D5: Qtde Un. | E5: A Vista | F5: A Prazo | G5: Total | H5: Custo | I5: Lucro Bruto | J5: Lucro Líquido | K5: Marg. Bruta | L5: Marg. Líquida | M5: PMP
A6: 10001 | B6: CILINDRO PNEUMATICO PARA BLOQUEIO | C6: 1310 | D6: 1310 | E6: 1925 | F6: 38474.14 | G6: 40399.14 | H6: 17846.49 | I6: 22552.65 | J6: 11451.79 | K6: 0.5582 | L6: 0.2835 | M6: 40.26
A7: 10002 | B7: CONJUNTO VALVULA EVACUACAO SANITARIO | C7: 250 | D7: 250 | E7: 1956.13 | F7: 79203.85 | G7: 81159.98 | H7: 21253.55 | I7: 59906.43 | J7: 38372.42 | K7: 0.7381 | L7: 0.4728 | M7: 45.49
A8: 10004 | B8: CONJUNTO CONTROLE DETERGENTE | C8: 8 | D8: 8 | E8: 0 | F8: 765.28 | G8: 765.28 | H8: 385.84 | I8: 379.44 | J8: 169.22 | K8: 0.4958 | L8: 0.2211 | M8: 44.19
A9: 10005 | B9: BOMBA DOSADORA BACTERICIDA | C9: 676 | D9: 676 | E9: 129.25 | F9: 65422.73 | G9: 65551.98 | H9: 17509.348 | I9: 48042.63 | J9: 31429.9 | K9: 0.7329 | L9: 0.4795 | M9: 40.73
A10: 10006 | B10: VALVULA DE RETENCAO | C10: 36 | D10: 36 | E10: 190.84 | F10: 2150.88 | G10: 2341.72 | H10: 355.37 | I10: 1986.35 | J10: 1343.05 | K10: 0.8482 | L10: 0.5735 | M10: 45.96
A11: 10007 | B11: CONJUNTO VALVULA EVACUACAO SANITARIO | C11: 343 | D11: 343 | E11: 0 | F11: 105985.38 | G11: 105985.38 | H11: 29514.245 | I11: 76471.14 | J11: 49008.67 | K11: 0.7215 | L11: 0.4624 | M11: 45.61
A12: 10008 | B12: VALVULA DE CALEFACAO 24V | C12: 1946 | D12: 1946 | E12: 8898.96 | F12: 305207.82 | G12: 314106.78 | H12: 131721.21 | I12: 182385.58 | J12: 101478.87 | K12: 0.5806 | L12: 0.3231 | M12: 44.96
A13: 10012 | B13: VALVULA DE RETENCAO CINZA | C13: 1 | D13: 1 | E13: 0 | F13: 55.8 | G13: 55.8 | H13: 10.27 | I13: 45.53 | J13: 30.2 | K13: 0.8159 | L13: 0.5412 | M13: 50
A14: 10018 | B14: VALVULA DE RETENCAO | C14: 16 | D14: 16 | E14: 0 | F14: 1332.4 | G14: 1332.4 | H14: 551.71 | I14: 780.69 | J14: 430.05 | K14: 0.5859 | L14: 0.3228 | M14: 50
A15: 10021 | B15: CONJUNTO VALVULA EVACUACAO CAIXA DETRITO DD | C15: 7 | D15: 7 | E15: 0 | F15: 2920.89 | G15: 2920.89 | H15: 527.38 | I15: 2393.51 | J15: 1591.08 | K15: 0.8194 | L15: 0.5447 | M15: 45
A16: 10022 | B16: CONJUNTO VALVULA EVACUACAO CAIXA DETRITO | C16: 1 | D16: 1 | E16: 0 | F16: 356.28 | G16: 356.28 | H16: 80.79 | I16: 275.49 | J16: 177.61 | K16: 0.7732 | L16: 0.4985 | M16: 60
A17: 10024 | B17: DOBRADICA ASSENTO SANITARIO | C17: 247 | D17: 247 | E17: 0 | F17: 11920.22 | G17: 11920.22 | H17: 1827.966 | I17: 10092.25 | J17: 6817.53 | K17: 0.8466 | L17: 0.5719 | M17: 50
... A290: 90746 | B290: CAIXA DE JUNCAO | C290: 1 | D290: 1 | E290: 0 | F290: 592.33 | G290: 592.33 | H290: 68.64 | I290: 523.69 | J290: 389.5 | K290: 0.8841 | L290: 0.6576 | M290: 30
A291: TOTAL GERAL | B291: =COUNTA(A6:A290)&" produtos" -> 285 produtos | C291: =SUM(C6:C290) -> 759064.5 | D291: =SUM(D6:D290) -> 759064.5 | E291: =SUM(E6:E290) -> 54369.99 | F291: =SUM(F6:F290) -> 5194820.4 | G291: =SUM(G6:G290) -> 5249190.4 | H291: =SUM(H6:H290) -> 2594338.5 | I291: =SUM(I6:I290) -> 2654852 | J291: =SUM(J6:J290) -> 1310861 | K291: =IFERROR(I291/G291,0) -> 0.50576409 | L291: =IFERROR(J291/G291,0) -> 0.24972633 | M291: =IFERROR(SUMPRODUCT(M6:M290,G6:G290)/G291,0) -> 44.172248

Sheet Matriz 08
A1: INDUSTRIA SCHUMACHER LTDA — Matriz
A2: Demonstrativo de Margens de Venda por Produto
A3: Período: 01/08/2026 a 31/08/2026 (Agosto/2026)
A5: Código | B5: Produto | C5: Qtde | D5: Qtde Un. | E5: A Vista | F5: A Prazo | G5: Total | H5: Custo | I5: Lucro Bruto | J5: Lucro Líquido | K5: Marg. Bruta | L5: Marg. Líquida | M5: PMP
A6: 10001 | B6: CILINDRO PNEUMATICO PARA BLOQUEIO | C6: 1709 | D6: 1709 | E6: 0 | F6: 50852.82 | G6: 50852.82 | H6: 22182.654 | I6: 28670.18 | J6: 14992.22 | K6: 0.5638 | L6: 0.2948 | M6: 43.01
A7: 10002 | B7: CONJUNTO VALVULA EVACUACAO SANITARIO | C7: 288 | D7: 288 | E7: 0 | F7: 92154.77 | G7: 92154.77 | H7: 24209.369 | I7: 67945.4 | J7: 43441.91 | K7: 0.7373 | L7: 0.4714 | M7: 46.35
A8: 10004 | B8: CONJUNTO CONTROLE DETERGENTE | C8: 4 | D8: 4 | E8: 0 | F8: 396 | G8: 396 | H8: 192.9101 | I8: 203.09 | J8: 94.31 | K8: 0.5129 | L8: 0.2382 | M8: 52.5
A9: 10005 | B9: BOMBA DOSADORA BACTERICIDA | C9: 797 | D9: 797 | E9: 0 | F9: 74612.1 | G9: 74612.1 | H9: 16251.23 | I9: 58360.87 | J9: 39567.33 | K9: 0.7822 | L9: 0.5303 | M9: 44.79
A10: 10006 | B10: VALVULA DE RETENCAO | C10: 45 | D10: 45 | E10: 0 | F10: 2566.8 | G10: 2566.8 | H10: 438.8 | I10: 2128 | J10: 1422.85 | K10: 0.829 | L10: 0.5543 | M10: 50.91
A11: 10007 | B11: CONJUNTO VALVULA EVACUACAO SANITARIO | C11: 390 | D11: 390 | E11: 0 | F11: 114056.17 | G11: 114056.17 | H11: 32662.421 | I11: 81393.75 | J11: 55744.4 | K11: 0.7136 | L11: 0.4887 | M11: 44.13
A12: 10008 | B12: VALVULA DE CALEFACAO 24V | C12: 2061 | D12: 2061 | E12: 0 | F12: 340795.07 | G12: 340795.07 | H12: 139131.6 | I12: 201663.48 | J12: 121920.63 | K12: 0.5917 | L12: 0.3578 | M12: 47.95
A13: 10018 | B13: VALVULA DE RETENCAO | C13: 27 | D13: 27 | E13: 0 | F13: 2268.72 | G13: 2268.72 | H13: 929.99 | I13: 1338.73 | J13: 743.45 | K13: 0.5901 | L13: 0.3277 | M13: 50.45
A14: 10019 | B14: CONJUNTO VALVULA EVACUACAO SANITARIO | C14: 2 | D14: 2 | E14: 0 | F14: 577.8 | G14: 577.8 | H14: 150.25 | I14: 427.55 | J14: 296.65 | K14: 0.74 | L14: 0.5134 | M14: 7
A15: 10021 | B15: CONJUNTO VALVULA EVACUACAO CAIXA DETRITO DD | C15: 47 | D15: 47 | E15: 0 | F15: 19611.69 | G15: 19611.69 | H15: 3625.3107 | I15: 15986.38 | J15: 10598.65 | K15: 0.8151 | L15: 0.5404 | M15: 45.36
A16: 10022 | B16: CONJUNTO VALVULA EVACUACAO CAIXA DETRITO | C16: 1 | D16: 1 | E16: 0 | F16: 356.28 | G16: 356.28 | H16: 80.79 | I16: 275.49 | J16: 177.61 | K16: 0.7732 | L16: 0.4985 | M16: 57
A17: 10024 | B17: DOBRADICA ASSENTO SANITARIO | C17: 304 | D17: 304 | E17: 0 | F17: 14690.34 | G17: 14690.34 | H17: 2248.316 | I17: 12442.03 | J17: 8406.3 | K17: 0.847 | L17: 0.5722 | M17: 49.84
... A275: 90766 | B275: CAIXA DE JUNCAO | C275: 5 | D275: 5 | E275: 0 | F275: 1579.5 | G275: 1579.5 | H275: 440.57 | I275: 1138.93 | J275: 705.01 | K275: 0.7211 | L275: 0.4464 | M275: 46
A276: TOTAL GERAL | B276: =COUNTA(A6:A275)&" produtos" -> 270 produtos | C276: =SUM(C6:C275) -> 41332 | D276: =SUM(D6:D275) -> 41332 | E276: =SUM(E6:E275) -> 2176.91 | F276: =SUM(F6:F275) -> 4934281.8 | G276: =SUM(G6:G275) -> 4936458.7 | H276: =SUM(H6:H275) -> 2062446 | I276: =SUM(I6:I275) -> 2874012.9 | J276: =SUM(J6:J275) -> 1663650.6 | K276: =IFERROR(I276/G276,0) -> 0.58220134 | L276: =IFERROR(J276/G276,0) -> 0.33701297 | M276: =IFERROR(SUMPRODUCT(M6:M275,G6:G275)/G276,0) -> 40.059092

Sheet Filial 01
A1: INDUSTRIA SCHUMACHER LTDA — Filial: SCHUMACHER SERVICOS
A2: Demonstrativo de Margens de Venda por Produto
A3: Período: 01/01/2026 a 31/01/2026 (Janeiro/2026)
A5: Código | B5: Produto | C5: Qtde | D5: Qtde Un. | E5: A Vista | F5: A Prazo | G5: Total | H5: Custo | I5: Lucro Bruto | J5: Lucro Líquido | K5: Marg. Bruta | L5: Marg. Líquida | M5: PMP
A6: 10585 | B6: CAIXA ROTO | C6: 14 | D6: 14 | E6: 0 | F6: 3382 | G6: 3382 | H6: 2870.04 | I6: 511.96 | J6: -431.91 | K6: 0.1514 | L6: -0.1277 | M6: 45.78
A7: 10586 | B7: ADAPTADOR MANG. | C7: 753 | D7: 753 | E7: 0 | F7: 4641.6 | G7: 4641.6 | H7: 2334.8394 | I7: 2306.76 | J7: 1011.32 | K7: 0.497 | L7: 0.2179 | M7: 45.5
A8: 10588 | B8: DUTO | C8: 120 | D8: 120 | E8: 0 | F8: 1370 | G8: 1370 | H8: 675 | I8: 695 | J8: 312.68 | K8: 0.5073 | L8: 0.2282 | M8: 45.68
A9: 10664 | B9: PEÇA VARIVELOX | C9: 880 | D9: 880 | E9: 0 | F9: 19272 | G9: 19272 | H9: 1873.784 | I9: 17398.22 | J9: 12103.82 | K9: 0.9028 | L9: 0.6281 | M9: 28
A10: 10704 | B10: CHAPA POLTRONA | C10: 50 | D10: 50 | E10: 0 | F10: 535 | G10: 535 | H10: 183.22 | I10: 351.78 | J10: 202.47 | K10: 0.6575 | L10: 0.3784 | M10: 47
A11: 90006 | B11: INDUSTRIALIZAÇÃO POR ENCOMENDA | C11: 14 | D11: 14 | E11: 0 | F11: 20441.2 | G11: 20441.2 | H11: 17875.11 | I11: 2566.09 | J11: -117.35 | K11: 0.1255 | L11: -0.0057 | M11: 53.63
A12: 90026 | B12: DIVISOR MENOR | C12: 29 | D12: 29 | E12: 0 | F12: 5220 | G12: 5220 | H12: 5220 | I12: 0 | J12: -1112.15 | K12: 0 | L12: -0.2131 | M12: 60
A13: 90027 | B13: DIVISOR MAIOR | C13: 32 | D13: 32 | E13: 0 | F13: 6688 | G13: 6688 | H13: 7040 | I13: -352 | J13: -1776.92 | K13: -0.0526 | L13: -0.2657 | M13: 60
A14: 90103 | B14: CHAPA | C14: 20 | D14: 20 | E14: 3874.78 | F14: 43081.12 | G14: 46955.9 | H14: 18034.6 | I14: 28921.3 | J14: 15532.29 | K14: 0.6159 | L14: 0.3308 | M14: 39.03
A15: 90144 | B15: BLINDAGEM | C15: 64 | D15: 64 | E15: 0 | F15: 4992 | G15: 4992 | H15: 2262.0032 | I15: 2730 | J15: 1666.43 | K15: 0.5469 | L15: 0.3338 | M15: 60
A16: 90237 | B16: PECAS ROTOMOLDADAS AERADOR PROPULSOR | C16: 46 | D16: 46 | E16: 0 | F16: 6854 | G16: 6854 | H16: 6393.8896 | I16: 460.11 | J16: -1422.83 | K16: 0.0671 | L16: -0.2076 | M16: 30
A17: 90238 | B17: CHAPA AERADOR PROPULSOR | C17: 500 | D17: 500 | E17: 0 | F17: 375 | G17: 375 | H17: 147012.2 | I17: -146637.2 | J17: -146740.22 | K17: -391.0325 | L17: -391.3073 | M17: 30
... A58: 90714 | B58: BICO LATERAL | C58: 35 | D58: 35 | E58: 0 | F58: 3806.25 | G58: 3806.25 | H58: 1309.43 | I58: 2496.82 | J58: 1685.88 | K58: 0.656 | L58: 0.4429 | M58: 60
A59: TOTAL GERAL | B59: =COUNTA(A6:A58)&" produtos" -> 53 produtos | C59: =SUM(C6:C58) -> 20908 | D59: =SUM(D6:D58) -> 20908 | E59: =SUM(E6:E58) -> 22380.27 | F59: =SUM(F6:F58) -> 708623.32 | G59: =SUM(G6:G58) -> 731003.59 | H59: =SUM(H6:H58) -> 562436.01 | I59: =SUM(I6:I58) -> 168567.6 | J59: =SUM(J6:J58) -> -6678.45 | K59: =IFERROR(I59/G59,0) -> 0.2305975 | L59: =IFERROR(J59/G59,0) -> -0.0091360016 | M59: =IFERROR(SUMPRODUCT(M6:M58,G6:G58)/G59,0) -> 49.244088

Sheet Filial 02
A1: INDUSTRIA SCHUMACHER LTDA — Filial: SCHUMACHER SERVICOS
A2: Demonstrativo de Margens de Venda por Produto
A3: Período: 01/02/2026 a 28/02/2026 (Fevereiro/2026)
A5: Código | B5: Produto | C5: Qtde | D5: Qtde Un. | E5: A Vista | F5: A Prazo | G5: Total | H5: Custo | I5: Lucro Bruto | J5: Lucro Líquido | K5: Marg. Bruta | L5: Marg. Líquida | M5: PMP
A6: 10585 | B6: CAIXA ROTO | C6: 26 | D6: 26 | E6: 0 | F6: 7186.4 | G6: 7186.4 | H6: 4541.61 | I6: 2644.79 | J6: 639.12 | K6: 0.368 | L6: 0.0889 | M6: 45.45
A7: 10586 | B7: ADAPTADOR MANG. | C7: 1104 | D7: 1104 | E7: 0 | F7: 6596.8 | G7: 6596.8 | H7: 2500.2546 | I7: 4096.55 | J7: 2255.34 | K7: 0.621 | L7: 0.3419 | M7: 45.89
A8: 10588 | B8: DUTO | C8: 250 | D8: 250 | E8: 0 | F8: 2620 | G8: 2620 | H8: 2617.56 | I8: 2.44 | J8: -728.74 | K8: 0.0009 | L8: -0.2781 | M8: 45.59
A9: 10664 | B9: PEÇA VARIVELOX | C9: 4512 | D9: 4512 | E9: 0 | F9: 34357.54 | G9: 34357.54 | H9: 5290.2436 | I9: 29067.3 | J9: 19628.59 | K9: 0.846 | L9: 0.5713 | M9: 28
A10: 10704 | B10: CHAPA POLTRONA | C10: 750 | D10: 750 | E10: 0 | F10: 8488 | G10: 8488 | H10: 2899.42 | I10: 5588.58 | J10: 3219.7 | K10: 0.6584 | L10: 0.3793 | M10: 47.54
A11: 10706 | B11: BOIA | C11: 6 | D11: 6 | E11: 0 | F11: 6105 | G11: 6105 | H11: 2001.6498 | I11: 4103.35 | J11: 2426.19 | K11: 0.6721 | L11: 0.3974 | M11: 45
A12: 52674 | B12: CAVACO DE INOX MACIÇO | C12: 2320.7 | D12: 2320.7 | E12: 8586.59 | F12: 0 | G12: 8586.59 | H12: 6497.96 | I12: 2088.63 | J12: 1035.91 | K12: 0.2432 | L12: 0.1206 | M12: 7
A13: 52676 | B13: CAVACO DE FERRO | C13: 1470 | D13: 1470 | E13: 294 | F13: 0 | G13: 294 | H13: 73.5 | I13: 220.5 | J13: 184.45 | K13: 0.75 | L13: 0.6274 | M13: 7
A14: 55954 | B14: INSERTO M8 X 16 MM | C14: 100 | D14: 100 | E14: 0 | F14: 400 | G14: 400 | H14: 363.32 | I14: 36.68 | J14: -73.21 | K14: 0.0917 | L14: -0.183 | M14: 30
A15: 56047 | B15: INSERTO SEXTAVADO | C15: 414 | D15: 414 | E15: 0 | F15: 1233.72 | G15: 1233.72 | H15: 674.1162 | I15: 559.6 | J15: 220.68 | K15: 0.4536 | L15: 0.1789 | M15: 44
A16: 56365 | B16: INSERTO ROSCA | C16: 24 | D16: 24 | E16: 0 | F16: 192 | G16: 192 | H16: 189.6696 | I16: 2.33 | J16: -66.09 | K16: 0.0121 | L16: -0.3442 | M16: 30
A17: 57502 | B17: CAVACO DE ACO | C17: 11312.6 | D17: 11312.6 | E17: 7918.82 | F17: 0 | G17: 7918.82 | H17: 0 | I17: 7918.82 | J17: 7918.82 | K17: 1 | L17: 1 | M17: 7
... A78: 90725 | B78: BICO CENTRAL 45/50 CM | C78: 50 | D78: 50 | E78: 0 | F78: 5940 | G78: 5940 | H78: 3768.42 | I78: 2171.58 | J78: 906.03 | K78: 0.3656 | L78: 0.1525 | M78: 60
A79: TOTAL GERAL | B79: =COUNTA(A6:A78)&" produtos" -> 73 produtos | C79: =SUM(C6:C78) -> 52309.3 | D79: =SUM(D6:D78) -> 52309.3 | E79: =SUM(E6:E78) -> 50001.56 | F79: =SUM(F6:F78) -> 1663417.9 | G79: =SUM(G6:G78) -> 1713419.5 | H79: =SUM(H6:H78) -> 1901056 | I79: =SUM(I6:I78) -> -187636.43 | J79: =SUM(J6:J78) -> -619739.23 | K79: =IFERROR(I79/G79,0) -> -0.10950992 | L79: =IFERROR(J79/G79,0) -> -0.36169732 | M79: =IFERROR(SUMPRODUCT(M6:M78,G6:G78)/G79,0) -> 49.795065

Sheet Filial 03
A1: INDUSTRIA SCHUMACHER LTDA — Filial: SCHUMACHER SERVICOS
A2: Demonstrativo de Margens de Venda por Produto
A3: Período: 01/03/2026 a 31/03/2026 (Março/2026)
A5: Código | B5: Produto | C5: Qtde | D5: Qtde Un. | E5: A Vista | F5: A Prazo | G5: Total | H5: Custo | I5: Lucro Bruto | J5: Lucro Líquido | K5: Marg. Bruta | L5: Marg. Líquida | M5: PMP
A6: 10585 | B6: CAIXA ROTO | C6: 37 | D6: 37 | E6: 0 | F6: 12006.6 | G6: 12006.6 | H6: 5086.2601 | I6: 6920.34 | J6: 3569.37 | K6: 0.5764 | L6: 0.2973 | M6: 46.01
A7: 10586 | B7: ADAPTADOR MANG. | C7: 1241 | D7: 1241 | E7: 0 | F7: 7079.45 | G7: 7079.45 | H7: 2275.5797 | I7: 4803.87 | J7: 2828.05 | K7: 0.6786 | L7: 0.3995 | M7: 46.11
A8: 10588 | B8: DUTO | C8: 440 | D8: 440 | E8: 0 | F8: 6483 | G8: 6483 | H8: 4098.5 | I8: 2384.5 | J8: 575.02 | K8: 0.3678 | L8: 0.0887 | M8: 46.15
A9: 10664 | B9: PEÇA VARIVELOX | C9: 1897 | D9: 1897 | E9: 0 | F9: 25984.66 | G9: 25984.66 | H9: 2944.1228 | I9: 23040.54 | J9: 15902.04 | K9: 0.8867 | L9: 0.612 | M9: 28
A10: 10668 | B10: PEÇA AGROBARTT | C10: 430 | D10: 430 | E10: 0 | F10: 1293.2 | G10: 1293.2 | H10: 136588.08 | I10: -135294.88 | J10: -135650.14 | K10: -104.6202 | L10: -104.8949 | M10: 38.74
A11: 10704 | B11: CHAPA POLTRONA | C11: 882 | D11: 882 | E11: 0 | F11: 11419.68 | G11: 11419.68 | H11: 4520.9432 | I11: 6898.73 | J11: 3711.51 | K11: 0.6041 | L11: 0.325 | M11: 47.58
A12: 10706 | B12: BOIA | C12: 6 | D12: 6 | E12: 0 | F12: 5772 | G12: 5772 | H12: 1869.03 | I12: 3902.97 | J12: 2317.28 | K12: 0.6762 | L12: 0.4015 | M12: 47.1
A13: 10729 | B13: CONJ. POLTRONA OBESO | C13: 3 | D13: 3 | E13: 0 | F13: 4143.27 | G13: 4143.27 | H13: 340.95 | I13: 3802.32 | J13: 2645.93 | K13: 0.9177 | L13: 0.6386 | M13: 45
A14: 52674 | B14: CAVACO DE INOX MACIÇO | C14: 2590 | D14: 2590 | E14: 9345 | F14: 0 | G14: 9345 | H14: 7252 | I14: 2093 | J14: 947.3 | K14: 0.224 | L14: 0.1014 | M14: 7
A15: 53438 | B15: CAIXA DE DETRITOS | C15: 5 | D15: 5 | E15: 1270.7 | F15: 0 | G15: 1270.7 | H15: 478.13 | I15: 792.57 | J15: 443.49 | K15: 0.6237 | L15: 0.349 | M15: 7
A16: 55954 | B16: INSERTO M8 X 16 MM | C16: 16 | D16: 16 | E16: 0 | F16: 64 | G16: 64 | H16: 58.1296 | I16: 5.87 | J16: -11.71 | K16: 0.0917 | L16: -0.183 | M16: 30
A17: 56047 | B17: INSERTO SEXTAVADO | C17: 1566 | D17: 1566 | E17: 0 | F17: 4648.32 | G17: 4648.32 | H17: 2609.892 | I17: 2038.43 | J17: 761.44 | K17: 0.4385 | L17: 0.1638 | M17: 51.3
... A82: 90740 | B82: SUPORTE TUBO | C82: 6 | D82: 6 | E82: 0 | F82: 361.98 | G82: 361.98 | H82: 162.1698 | I82: 199.81 | J82: 100.36 | K82: 0.552 | L82: 0.2773 | M82: 30
A83: TOTAL GERAL | B83: =COUNTA(A6:A82)&" produtos" -> 77 produtos | C83: =SUM(C6:C82) -> 42566 | D83: =SUM(D6:D82) -> 42566 | E83: =SUM(E6:E82) -> 54740.53 | F83: =SUM(F6:F82) -> 1414757.4 | G83: =SUM(G6:G82) -> 1469497.9 | H83: =SUM(H6:H82) -> 3423774.2 | I83: =SUM(I6:I82) -> -1954276.3 | J83: =SUM(J6:J82) -> -2309105.1 | K83: =IFERROR(I83/G83,0) -> -1.3298938 | L83: =IFERROR(J83/G83,0) -> -1.5713564 | M83: =IFERROR(SUMPRODUCT(M6:M82,G6:G82)/G83,0) -> 51.98175

Sheet Filial 04
A1: INDUSTRIA SCHUMACHER LTDA — Filial: SCHUMACHER SERVICOS
A2: Demonstrativo de Margens de Venda por Produto
A3: Período: 01/04/2026 a 30/04/2026 (Abril/2026)
A5: Código | B5: Produto | C5: Qtde | D5: Qtde Un. | E5: A Vista | F5: A Prazo | G5: Total | H5: Custo | I5: Lucro Bruto | J5: Lucro Líquido | K5: Marg. Bruta | L5: Marg. Líquida | M5: PMP
A6: 10585 | B6: CAIXA ROTO | C6: 22 | D6: 22 | E6: 0 | F6: 5423 | G6: 5423 | H6: 3074.18 | I6: 2348.82 | J6: 835.26 | K6: 0.4331 | L6: 0.154 | M6: 46.29
A7: 10586 | B7: ADAPTADOR MANG. | C7: 1107 | D7: 1107 | E7: 0 | F7: 6212.15 | G7: 6212.15 | H7: 2243.6212 | I7: 3968.52 | J7: 2234.74 | K7: 0.6388 | L7: 0.3597 | M7: 46.41
A8: 10588 | B8: DUTO | C8: 310 | D8: 310 | E8: 0 | F8: 3992 | G8: 3992 | H8: 1698.82 | I8: 2293.18 | J8: 1179.13 | K8: 0.5744 | L8: 0.2954 | M8: 46.77
A9: 10664 | B9: PEÇA VARIVELOX | C9: 4081 | D9: 4081 | E9: 0 | F9: 28849.78 | G9: 28849.78 | H9: 4295.363 | I9: 24554.42 | J9: 16628.81 | K9: 0.8511 | L9: 0.5764 | M9: 28
A10: 10704 | B10: CHAPA POLTRONA | C10: 1003 | D10: 1003 | E10: 0 | F10: 11612.33 | G10: 11612.33 | H10: 4496.1866 | I10: 7116.14 | J10: 3875.18 | K10: 0.6128 | L10: 0.3337 | M10: 47.81
A11: 52674 | B11: CAVACO DE INOX MACIÇO | C11: 2170 | D11: 2170 | E11: 8029 | F11: 0 | G11: 8029 | H11: 6076 | I11: 1953 | J11: 968.64 | K11: 0.2432 | L11: 0.1206 | M11: 7
A12: 52676 | B12: CAVACO DE FERRO | C12: 1447.7 | D12: 1447.7 | E12: 289.54 | F12: 0 | G12: 289.54 | H12: 72.385 | I12: 217.16 | J12: 181.66 | K12: 0.75 | L12: 0.6274 | M12: 7
A13: 55954 | B13: INSERTO M8 X 16 MM | C13: 24 | D13: 24 | E13: 0 | F13: 96 | G13: 96 | H13: 87.1992 | I13: 8.8 | J13: -17.57 | K13: 0.0917 | L13: -0.183 | M13: 30
A14: 56047 | B14: INSERTO SEXTAVADO | C14: 1089 | D14: 1089 | E14: 0 | F14: 3245.22 | G14: 3245.22 | H14: 1810.3536 | I14: 1434.87 | J14: 543.34 | K14: 0.4421 | L14: 0.1674 | M14: 49.69
A15: 56365 | B15: INSERTO ROSCA | C15: 24 | D15: 24 | E15: 0 | F15: 192 | G15: 192 | H15: 189.6696 | I15: 2.33 | J15: -50.42 | K15: 0.0121 | L15: -0.2626 | M15: 30
A16: 57502 | B16: CAVACO DE ACO | C16: 9857.1 | D16: 9857.1 | E16: 6324.95 | F16: 0 | G16: 6324.95 | H16: 0 | I16: 6324.95 | J16: 6324.95 | K16: 1 | L16: 1 | M16: 7
A17: 57798 | B17: BOIA AERADOR | C17: 17 | D17: 17 | E17: 3024 | F17: 4320 | G17: 7344 | H17: 2160.2198 | I17: 5183.78 | J17: 2947.71 | K17: 0.7059 | L17: 0.4014 | M17: 38.24
... A85: 90747 | B85: PEÇAS MILKVEL | C85: 150 | D85: 150 | E85: 0 | F85: 3174 | G85: 3174 | H85: 1425.6 | I85: 1748.4 | J85: 876.44 | K85: 0.5509 | L85: 0.2761 | M85: 30
A86: TOTAL GERAL | B86: =COUNTA(A6:A85)&" produtos" -> 80 produtos | C86: =SUM(C6:C85) -> 44852.8 | D86: =SUM(D6:D85) -> 44852.8 | E86: =SUM(E6:E85) -> 57231.1 | F86: =SUM(F6:F85) -> 1161191.2 | G86: =SUM(G6:G85) -> 1218422.3 | H86: =SUM(H6:H85) -> 1465342.2 | I86: =SUM(I6:I85) -> -246919.78 | J86: =SUM(J6:J85) -> -520676.34 | K86: =IFERROR(I86/G86,0) -> -0.20265533 | L86: =IFERROR(J86/G86,0) -> -0.4273365 | M86: =IFERROR(SUMPRODUCT(M6:M85,G6:G85)/G86,0) -> 47.376628

Sheet Filial 05
A1: INDUSTRIA SCHUMACHER LTDA — Filial: SCHUMACHER SERVICOS
A2: Demonstrativo de Margens de Venda por Produto
A3: Período: 01/05/2026 a 31/05/2026 (Maio/2026)
A5: Código | B5: Produto | C5: Qtde | D5: Qtde Un. | E5: A Vista | F5: A Prazo | G5: Total | H5: Custo | I5: Lucro Bruto | J5: Lucro Líquido | K5: Marg. Bruta | L5: Marg. Líquida | M5: PMP
A6: 10585 | B6: CAIXA ROTO | C6: 22 | D6: 22 | E6: 0 | F6: 5645.2 | G6: 5645.2 | H6: 3385.5 | I6: 2259.7 | J6: 684.12 | K6: 0.4003 | L6: 0.1212 | M6: 45.12
A7: 10586 | B7: ADAPTADOR MANG. | C7: 1159 | D7: 1159 | E7: 0 | F7: 6905.05 | G7: 6905.05 | H7: 2692.9869 | I7: 4212.06 | J7: 2284.89 | K7: 0.61 | L7: 0.3309 | M7: 45.41
A8: 10588 | B8: DUTO | C8: 300 | D8: 300 | E8: 0 | F8: 3949 | G8: 3949 | H8: 2705.39 | I8: 1243.61 | J8: 141.38 | K8: 0.3149 | L8: 0.0358 | M8: 45.36
A9: 10664 | B9: PEÇA VARIVELOX | C9: 2868 | D9: 2868 | E9: 0 | F9: 21354.8 | G9: 21354.8 | H9: 3077.6938 | I9: 18277.11 | J9: 12410.51 | K9: 0.8559 | L9: 0.5812 | M9: 28
A10: 10704 | B10: CHAPA POLTRONA | C10: 250 | D10: 250 | E10: 0 | F10: 2675 | G10: 2675 | H10: 762.21 | I10: 1912.79 | J10: 1166.2 | K10: 0.7151 | L10: 0.436 | M10: 46.2
A11: 52674 | B11: CAVACO DE INOX MACIÇO | C11: 2350 | D11: 2350 | E11: 8695 | F11: 0 | G11: 8695 | H11: 6580 | I11: 2115 | J11: 1049 | K11: 0.2432 | L11: 0.1206 | M11: 7
A12: 52676 | B12: CAVACO DE FERRO | C12: 3190 | D12: 3190 | E12: 638 | F12: 0 | G12: 638 | H12: 159.5 | I12: 478.5 | J12: 400.28 | K12: 0.75 | L12: 0.6274 | M12: 7
A13: 55954 | B13: INSERTO M8 X 16 MM | C13: 148 | D13: 148 | E13: 0 | F13: 592 | G13: 592 | H13: 537.7188 | I13: 54.28 | J13: -108.35 | K13: 0.0917 | L13: -0.183 | M13: 30
A14: 56047 | B14: INSERTO SEXTAVADO | C14: 351 | D14: 351 | E14: 0 | F14: 1045.98 | G14: 1045.98 | H14: 583.5024 | I14: 462.48 | J14: 175.13 | K14: 0.4421 | L14: 0.1674 | M14: 29.23
A15: 56365 | B15: INSERTO ROSCA | C15: 216 | D15: 216 | E15: 0 | F15: 1728 | G15: 1728 | H15: 1707.0264 | I15: 20.97 | J15: -453.74 | K15: 0.0121 | L15: -0.2626 | M15: 30
A16: 57502 | B16: CAVACO DE ACO | C16: 9700 | D16: 9700 | E16: 6790 | F16: 0 | G16: 6790 | H16: 0 | I16: 6790 | J16: 6790 | K16: 1 | L16: 1 | M16: 7
A17: 57510 | B17: TUBO ESTRUTURA PROPULSOR | C17: 300 | D17: 300 | E17: 0 | F17: 1431 | G17: 1431 | H17: 1413.18 | I17: 17.82 | J17: -375.3 | K17: 0.0125 | L17: -0.2623 | M17: 30
... A75: 90753 | B75: TUBO TECSOFT | C75: 7 | D75: 7 | E75: 0 | F75: 187.81 | G75: 187.81 | H75: 0.56 | I75: 187.25 | J75: 135.66 | K75: 0.997 | L75: 0.7223 | M75: 28
A76: TOTAL GERAL | B76: =COUNTA(A6:A75)&" produtos" -> 70 produtos | C76: =SUM(C6:C75) -> 45036 | D76: =SUM(D6:D75) -> 45036 | E76: =SUM(E6:E75) -> 55558.29 | F76: =SUM(F6:F75) -> 1382332.6 | G76: =SUM(G6:G75) -> 1437890.9 | H76: =SUM(H6:H75) -> 1792939.6 | I76: =SUM(I6:I75) -> -355048.72 | J76: =SUM(J6:J75) -> -701181.94 | K76: =IFERROR(I76/G76,0) -> -0.24692327 | L76: =IFERROR(J76/G76,0) -> -0.48764615 | M76: =IFERROR(SUMPRODUCT(M6:M75,G6:G75)/G76,0) -> 54.526598

Sheet Filial 06
A1: INDUSTRIA SCHUMACHER LTDA — Filial: SCHUMACHER SERVICOS
A2: Demonstrativo de Margens de Venda por Produto
A3: Período: 01/06/2026 a 30/06/2026 (Junho/2026)
A5: Código | B5: Produto | C5: Qtde | D5: Qtde Un. | E5: A Vista | F5: A Prazo | G5: Total | H5: Custo | I5: Lucro Bruto | J5: Lucro Líquido | K5: Marg. Bruta | L5: Marg. Líquida | M5: PMP
A6: 10585 | B6: CAIXA ROTO | C6: 25 | D6: 25 | E6: 0 | F6: 5700 | G6: 5700 | H6: 4509.48 | I6: 1190.52 | J6: -400.32 | K6: 0.2089 | L6: -0.0702 | M6: 45.6
A7: 10586 | B7: ADAPTADOR MANG. | C7: 1230 | D7: 1230 | E7: 0 | F7: 7721.75 | G7: 7721.75 | H7: 2902.51 | I7: 4819.24 | J7: 2664.1 | K7: 0.6241 | L7: 0.345 | M7: 45.61
A8: 10588 | B8: DUTO | C8: 429 | D8: 429 | E8: 0 | F8: 6950.7 | G8: 6950.7 | H8: 7505.133 | I8: -554.43 | J8: -2494.25 | K8: -0.0798 | L8: -0.3588 | M8: 45.62
A9: 10599 | B9: DIVISORIA | C9: 1 | D9: 1 | E9: 0 | F9: 312.4 | G9: 312.4 | H9: 175.5 | I9: 136.9 | J9: 49.71 | K9: 0.4382 | L9: 0.1591 | M9: 45
A10: 10664 | B10: PEÇA VARIVELOX | C10: 3930 | D10: 3930 | E10: 0 | F10: 24893.62 | G10: 24893.62 | H10: 3114.8532 | I10: 21778.77 | J10: 14940.01 | K10: 0.8749 | L10: 0.6002 | M10: 28.05
A11: 10668 | B11: PEÇA AGROBARTT | C11: 35 | D11: 35 | E11: 0 | F11: 284.2 | G11: 284.2 | H11: 52.74 | I11: 231.46 | J11: 153.41 | K11: 0.8144 | L11: 0.5398 | M11: 31
A12: 10729 | B12: CONJ. POLTRONA OBESO | C12: 1 | D12: 1 | E12: 0 | F12: 1381.09 | G12: 1381.09 | H12: 295.39 | I12: 1085.7 | J12: 700.23 | K12: 0.7861 | L12: 0.507 | M12: 46
A13: 52674 | B13: CAVACO DE INOX MACIÇO | C13: 1600 | D13: 1600 | E13: 5920 | F13: 0 | G13: 5920 | H13: 4480 | I13: 1440 | J13: 714.21 | K13: 0.2432 | L13: 0.1206 | M13: 7
A14: 52676 | B14: CAVACO DE FERRO | C14: 590 | D14: 590 | E14: 118 | F14: 0 | G14: 118 | H14: 29.5 | I14: 88.5 | J14: 74.03 | K14: 0.75 | L14: 0.6274 | M14: 7
A15: 55954 | B15: INSERTO M8 X 16 MM | C15: 48 | D15: 48 | E15: 0 | F15: 192 | G15: 192 | H15: 174.3888 | I15: 17.61 | J15: -35.14 | K15: 0.0917 | L15: -0.183 | M15: 30
A16: 56047 | B16: INSERTO SEXTAVADO | C16: 1881 | D16: 1881 | E16: 0 | F16: 5605.38 | G16: 5605.38 | H16: 3127.5387 | I16: 2477.85 | J16: 937.94 | K16: 0.442 | L16: 0.1673 | M16: 43.36
A17: 57502 | B17: CAVACO DE ACO | C17: 5430 | D17: 5430 | E17: 3801 | F17: 0 | G17: 3801 | H17: 0 | I17: 3801 | J17: 3801 | K17: 1 | L17: 1 | M17: 7
... A72: 90755 | B72: IND. INDUSCAVA | C72: 1052 | D72: 1052 | E72: 0 | F72: 3053.79 | G72: 3053.79 | H72: 0 | I72: 3053.79 | J72: 3053.79 | K72: 1 | L72: 1 | M72: 53
A73: TOTAL GERAL | B73: =COUNTA(A6:A72)&" produtos" -> 67 produtos | C73: =SUM(C6:C72) -> 44957 | D73: =SUM(D6:D72) -> 44957 | E73: =SUM(E6:E72) -> 54771.47 | F73: =SUM(F6:F72) -> 1421442.7 | G73: =SUM(G6:G72) -> 1476214.1 | H73: =SUM(H6:H72) -> 1614364.4 | I73: =SUM(I6:I72) -> -138150.15 | J73: =SUM(J6:J72) -> -487667.12 | K73: =IFERROR(I73/G73,0) -> -0.093584085 | L73: =IFERROR(J73/G73,0) -> -0.33034985 | M73: =IFERROR(SUMPRODUCT(M6:M72,G6:G72)/G73,0) -> 57.577334

Sheet Filial 07
A1: INDUSTRIA SCHUMACHER LTDA — Filial: SCHUMACHER SERVICOS
A2: Demonstrativo de Margens de Venda por Produto
A3: Período: 01/07/2026 a 31/07/2026 (Julho/2026)
A5: Código | B5: Produto | C5: Qtde | D5: Qtde Un. | E5: A Vista | F5: A Prazo | G5: Total | H5: Custo | I5: Lucro Bruto | J5: Lucro Líquido | K5: Marg. Bruta | L5: Marg. Líquida | M5: PMP
A6: 10585 | B6: CAIXA ROTO | C6: 3 | D6: 3 | E6: 0 | F6: 684 | G6: 684 | H6: 410.7 | I6: 273.3 | J6: 82.41 | K6: 0.3996 | L6: 0.1205 | M6: 46
A7: 10586 | B7: ADAPTADOR MANG. | C7: 579 | D7: 579 | E7: 0 | F7: 3515.55 | G7: 3515.55 | H7: 1108.585 | I7: 2406.97 | J7: 1425.83 | K7: 0.6847 | L7: 0.4056 | M7: 46.73
A8: 10588 | B8: DUTO | C8: 157 | D8: 157 | E8: 0 | F8: 2134.1 | G8: 2134.1 | H8: 911.096 | I8: 1223.01 | J8: 627.44 | K8: 0.5731 | L8: 0.294 | M8: 46.36
A9: 10664 | B9: PEÇA VARIVELOX | C9: 3550 | D9: 3550 | E9: 0 | F9: 13424.84 | G9: 13424.84 | H9: 2913.7324 | I9: 10511.1 | J9: 6823.04 | K9: 0.783 | L9: 0.5082 | M9: 28
A10: 10704 | B10: CHAPA POLTRONA | C10: 50 | D10: 50 | E10: 0 | F10: 535 | G10: 535 | H10: 156.48 | I10: 378.52 | J10: 229.21 | K10: 0.7075 | L10: 0.4284 | M10: 49
A11: 10729 | B11: CONJ. POLTRONA OBESO | C11: 1 | D11: 1 | E11: 0 | F11: 1371.09 | G11: 1371.09 | H11: 239.4 | I11: 1131.69 | J11: 749.02 | K11: 0.8254 | L11: 0.5463 | M11: 46
A12: 52674 | B12: CAVACO DE INOX MACIÇO | C12: 2760 | D12: 2760 | E12: 3219 | F12: 6993 | G12: 10212 | H12: 7728 | I12: 2484 | J12: 1232.01 | K12: 0.2432 | L12: 0.1206 | M12: 7
A13: 52676 | B13: CAVACO DE FERRO | C13: 2380 | D13: 2380 | E13: 254 | F13: 222 | G13: 476 | H13: 119 | I13: 357 | J13: 298.64 | K13: 0.75 | L13: 0.6274 | M13: 7
A14: 55954 | B14: INSERTO M8 X 16 MM | C14: 96 | D14: 96 | E14: 0 | F14: 470.4 | G14: 470.4 | H14: 348.7872 | I14: 121.61 | J14: -7.62 | K14: 0.2585 | L14: -0.0162 | M14: 30
A15: 56047 | B15: INSERTO SEXTAVADO | C15: 1062 | D15: 1062 | E15: 0 | F15: 3164.76 | G15: 3164.76 | H15: 1765.7874 | I15: 1398.97 | J15: 529.55 | K15: 0.442 | L15: 0.1673 | M15: 49.83
A16: 56365 | B16: INSERTO ROSCA | C16: 96 | D16: 96 | E16: 0 | F16: 768 | G16: 768 | H16: 829.3056 | I16: -61.31 | J16: -272.29 | K16: -0.0798 | L16: -0.3545 | M16: 30
A17: 57502 | B17: CAVACO DE ACO | C17: 8840 | D17: 8840 | E17: 2436 | F17: 3752 | G17: 6188 | H17: 0 | I17: 6188 | J17: 6188 | K17: 1 | L17: 1 | M17: 7
... A75: 90767 | B75: PEÇA | C75: 1 | D75: 1 | E75: 0 | F75: 521.07 | G75: 521.07 | H75: 205.81 | I75: 315.26 | J75: 170.15 | K75: 0.605 | L75: 0.3265 | M75: 7
A76: TOTAL GERAL | B76: =COUNTA(A6:A75)&" produtos" -> 70 produtos | C76: =SUM(C6:C75) -> 45132 | D76: =SUM(D6:D75) -> 45132 | E76: =SUM(E6:E75) -> 33009.57 | F76: =SUM(F6:F75) -> 1156281.7 | G76: =SUM(G6:G75) -> 1189291.3 | H76: =SUM(H6:H75) -> 1018171.4 | I76: =SUM(I6:I75) -> 171119.94 | J76: =SUM(J6:J75) -> -110692.35 | K76: =IFERROR(I76/G76,0) -> 0.14388396 | L76: =IFERROR(J76/G76,0) -> -0.093074211 | M76: =IFERROR(SUMPRODUCT(M6:M75,G6:G75)/G76,0) -> 45.848383

Sheet Filial 08
A1: INDUSTRIA SCHUMACHER LTDA — Filial: SCHUMACHER SERVICOS
A2: Demonstrativo de Margens de Venda por Produto
A3: Período: 01/08/2026 a 31/08/2026 (Agosto/2026)
A5: Código | B5: Produto | C5: Qtde | D5: Qtde Un. | E5: A Vista | F5: A Prazo | G5: Total | H5: Custo | I5: Lucro Bruto | J5: Lucro Líquido | K5: Marg. Bruta | L5: Marg. Líquida | M5: PMP
A6: 10585 | B6: CAIXA ROTO | C6: 12 | D6: 12 | E6: 0 | F6: 3476.9 | G6: 3476.9 | H6: 1874.64 | I6: 1602.26 | J6: 631.9 | K6: 0.4608 | L6: 0.1817 | M6: 45.78
A7: 10586 | B7: ADAPTADOR MANG. | C7: 1264 | D7: 1264 | E7: 0 | F7: 9141.19 | G7: 9141.19 | H7: 2540.3007 | I7: 6600.89 | J7: 4049.62 | K7: 0.7221 | L7: 0.443 | M7: 45.61
A8: 10588 | B8: DUTO | C8: 260 | D8: 260 | E8: 0 | F8: 5926.9 | G8: 5926.9 | H8: 2838.03 | I8: 3088.87 | J8: 1434.67 | K8: 0.5212 | L8: 0.2421 | M8: 45.64
A9: 10599 | B9: DIVISORIA | C9: 1 | D9: 1 | E9: 0 | F9: 376.29 | G9: 376.29 | H9: 175.5 | I9: 200.79 | J9: 95.77 | K9: 0.5336 | L9: 0.2545 | M9: 46
A10: 10664 | B10: PEÇA VARIVELOX | C10: 3107 | D10: 3107 | E10: 0 | F10: 35061.76 | G10: 35061.76 | H10: 3588.5589 | I10: 31473.21 | J10: 21841.06 | K10: 0.8977 | L10: 0.6229 | M10: 28
A11: 10704 | B11: CHAPA POLTRONA | C11: 300 | D11: 300 | E11: 0 | F11: 3210 | G11: 3210 | H11: 933.22 | I11: 2276.78 | J11: 1380.91 | K11: 0.7093 | L11: 0.4302 | M11: 45.67
A12: 52674 | B12: CAVACO DE INOX MACIÇO | C12: 1900 | D12: 1900 | E12: 7030 | F12: 0 | G12: 7030 | H12: 5320 | I12: 1710 | J12: -522.73 | K12: 0.2432 | L12: -0.0744 | M12: 7
A13: 52676 | B13: CAVACO DE FERRO | C13: 1460 | D13: 1460 | E13: 292 | F13: 0 | G13: 292 | H13: 73 | I13: 219 | J13: 126.26 | K13: 0.75 | L13: 0.4324 | M13: 7
A14: 55954 | B14: INSERTO M8 X 16 MM | C14: 108 | D14: 108 | E14: 0 | F14: 432 | G14: 432 | H14: 392.3856 | I14: 39.61 | J14: -79.06 | K14: 0.0917 | L14: -0.183 | M14: 30
A15: 56047 | B15: INSERTO SEXTAVADO | C15: 378 | D15: 378 | E15: 0 | F15: 1126.44 | G15: 1126.44 | H15: 697.41 | I15: 429.03 | J15: 119.57 | K15: 0.3809 | L15: 0.1061 | M15: 42
A16: 56365 | B16: INSERTO ROSCA | C16: 96 | D16: 96 | E16: 0 | F16: 768 | G16: 768 | H16: 829.3056 | I16: -61.31 | J16: -272.29 | K16: -0.0798 | L16: -0.3545 | M16: 30
A17: 57502 | B17: CAVACO DE ACO | C17: 7510 | D17: 7510 | E17: 5257 | F17: 0 | G17: 5257 | H17: 0 | I17: 5257 | J17: 5257 | K17: 1 | L17: 1 | M17: 7
... A69: 90774 | B69: GABARITO PLATAFORMA ELEVATORIA | C69: 8 | D69: 8 | E69: 0 | F69: 2675.52 | G69: 2675.52 | H69: 317.9498 | I69: 2357.57 | J69: 1622.55 | K69: 0.8812 | L69: 0.6064 | M69: 45
A70: TOTAL GERAL | B70: =COUNTA(A6:A69)&" produtos" -> 64 produtos | C70: =SUM(C6:C69) -> 40660 | D70: =SUM(D6:D69) -> 40660 | E70: =SUM(E6:E69) -> 33798.19 | F70: =SUM(F6:F69) -> 1302405 | G70: =SUM(G6:G69) -> 1336203.1 | H70: =SUM(H6:H69) -> 712345.39 | I70: =SUM(I6:I69) -> 623857.83 | J70: =SUM(J6:J69) -> 311079.03 | K70: =IFERROR(I70/G70,0) -> 0.46688846 | L70: =IFERROR(J70/G70,0) -> 0.23280818 | M70: =IFERROR(SUMPRODUCT(M6:M69,G6:G69)/G70,0) -> 49.208698
